[
  {
    "home_team": "Leicester City",
    "away_team": "Charlton Athletic",
    "home_draw_odds": 1.81,
    "away_draw_odds": 1.93,
    "home_away_odds": 1.27,
    "date": "31 Jan",
    "time": "14:30",
    "game_url": "https://betway.co.za/event/soccer/england/championship/leicester-city-charlton-athletic?eventId=61491007&fixtureType=highlights",
    "home_win": null,
    "draw": null,
    "away_win": null,
    "home_draw_no_bet": null,
    "away_draw_no_bet": null,
    "total_over_1.5": null,
    "total_under_3.5": null,
    "BTTS_yes": null,
    "BTTS_no": null,
    "home_team_over_0.5": 1.23,
    "away_team_over_0.5": 1.45,
    "match_confidence": 100.0,
    "match_id": 2335464,
    "pred": "X",
    "home_pred_score": 2,
    "away_pred_score": 2,
    "prob_1": 36,
    "prob_x": 40,
    "prob_2": 24,
    "avg_goals": 3.02,
    "kelly": 0.15,
    "game_link": "https://www.forebet.com/en/football/matches/leicester-city-charlton-athletic-2335464",
    "preview_link": "https://www.forebet.com/en/football-match-previews/25405-leicester-city-host-charlton-athletic-mid-table-rivals-set-for-a-cagey-championship-clash",
    "country": "England",
    "league_name": "Championship",
    "home_correct_score": 0,
    "away_correct_score": 2,
    "home_ht_score": 0,
    "away_ht_score": 2
  },
  {
    "home_team": "Sheffield Wednesday",
    "away_team": "Wrexham AFC",
    "home_draw_odds": 2.45,
    "away_draw_odds": 1.11,
    "home_away_odds": 1.19,
    "date": "31 Jan",
    "time": "14:30",
    "game_url": "https://betway.co.za/event/soccer/england/championship/sheffield-wednesday-wrexham-afc?eventId=61491019&fixtureType=highlights",
    "home_win": 6.8,
    "draw": 4.3,
    "away_win": 1.43,
    "home_draw_no_bet": 5.0,
    "away_draw_no_bet": 1.15,
    "total_over_1.5": 1.26,
    "total_under_3.5": 1.34,
    "BTTS_yes": 2.06,
    "BTTS_no": 1.71,
    "home_team_over_0.5": 1.8,
    "away_team_over_0.5": 1.12,
    "match_confidence": 100.0,
    "match_id": 2335467,
    "pred": "2",
    "home_pred_score": null,
    "away_pred_score": null,
    "prob_1": null,
    "prob_x": null,
    "prob_2": null,
    "avg_goals": null,
    "kelly": null,
    "game_link": "https://www.forebet.com/en/football/matches/sheffield-wednesday-wrexham-fc-2335467",
    "preview_link": null,
    "country": "England",
    "league_name": "Championship",
    "home_correct_score": 0,
    "away_correct_score": 1,
    "home_ht_score": 0,
    "away_ht_score": 0
  },
  {
    "home_team": "Stoke City",
    "away_team": "Southampton FC",
    "home_draw_odds": 1.69,
    "away_draw_odds": 2.09,
    "home_away_odds": 1.47,
    "date": "31 Jan",
    "time": "14:30",
    "game_url": "https://betway.co.za/event/soccer/england/championship/stoke-city-southampton-fc?eventId=61491021&fixtureType=highlights",
    "home_team_over_0.5": null,
    "away_team_over_0.5": null,
    "match_confidence": 100.0,
    "match_id": 2335472,
    "pred": "X",
    "home_pred_score": null,
    "away_pred_score": null,
    "prob_1": null,
    "prob_x": null,
    "prob_2": null,
    "avg_goals": null,
    "kelly": null,
    "game_link": "https://www.forebet.com/en/football/matches/stoke-city-southampton-2335472",
    "preview_link": null,
    "country": "England",
    "league_name": "Championship",
    "home_correct_score": 0,
    "away_correct_score": 2,
    "home_ht_score": 0,
    "away_ht_score": 1
  },
  {
    "home_team": "Northampton Town",
    "away_team": "Reading FC",
    "home_draw_odds": 1.54,
    "away_draw_odds": 1.36,
    "home_away_odds": 1.31,
    "date": "31 Jan",
    "time": "16:00",
    "game_url": "https://betway.co.za/event/soccer/england/league-one/northampton-town-reading-fc?eventId=61493435&fixtureType=highlights",
    "home_win": 2.9,
    "draw": 3.25,
    "away_win": 2.28,
    "home_draw_no_bet": 2.1,
    "away_draw_no_bet": 1.66,
    "total_over_1.5": 1.33,
    "total_under_3.5": 1.24,
    "BTTS_yes": 1.83,
    "BTTS_no": 1.87,
    "home_team_over_0.5": 1.39,
    "away_team_over_0.5": 1.29,
    "match_confidence": 100.0,
    "match_id": 2327011,
    "pred": "X",
    "home_pred_score": 0,
    "away_pred_score": 0,
    "prob_1": 26,
    "prob_x": 41,
    "prob_2": 33,
    "avg_goals": 2.03,
    "kelly": 0.14,
    "game_link": "https://www.forebet.com/en/football/matches/northampton-town-reading-2327011",
    "preview_link": null,
    "country": "England",
    "league_name": "League One",
    "home_correct_score": 0,
    "away_correct_score": 2,
    "home_ht_score": 0,
    "away_ht_score": 0
  },
  {
    "home_team": "Barnsley FC",
    "away_team": "Stevenage FC",
    "home_draw_odds": 1.33,
    "away_draw_odds": 1.56,
    "home_away_odds": 1.32,
    "date": "31 Jan",
    "time": "17:00",
    "game_url": "https://betway.co.za/event/soccer/england/league-one/barnsley-fc-stevenage-fc?eventId=61493421&fixtureType=highlights",
    "home_win": 2.22,
    "draw": 3.2,
    "away_win": 3.05,
    "home_draw_no_bet": 1.61,
    "away_draw_no_bet": 2.19,
    "total_over_1.5": 1.34,
    "total_under_3.5": 1.24,
    "BTTS_yes": 1.84,
    "BTTS_no": 1.86,
    "home_team_over_0.5": 1.28,
    "away_team_over_0.5": 1.41,
    "match_confidence": 100.0,
    "match_id": 2327003,
    "pred": "2",
    "home_pred_score": 0,
    "away_pred_score": 2,
    "prob_1": 32,
    "prob_x": 28,
    "prob_2": 40,
    "avg_goals": 2.38,
    "kelly": 0.11,
    "game_link": "https://www.forebet.com/en/football/matches/barnsley-stevenage-2327003",
    "preview_link": null,
    "country": "England",
    "league_name": "League One",
    "home_correct_score": 3,
    "away_correct_score": 1,
    "home_ht_score": 2,
    "away_ht_score": 1
  },
  {
    "home_team": "Burton Albion",
    "away_team": "Cardiff City",
    "home_draw_odds": 1.74,
    "away_draw_odds": 1.97,
    "home_away_odds": 1.86,
    "date": "31 Jan",
    "time": "17:00",
    "game_url": "https://betway.co.za/event/soccer/england/league-one/burton-albion-cardiff-city?eventId=61493425&fixtureType=highlights",
    "home_win": null,
    "draw": null,
    "away_win": null,
    "home_draw_no_bet": null,
    "away_draw_no_bet": null,
    "total_over_1.5": null,
    "total_under_3.5": null,
    "BTTS_yes": null,
    "BTTS_no": null,
    "home_team_over_0.5": 1.47,
    "away_team_over_0.5": 1.17,
    "match_confidence": 100.0,
    "match_id": 2327002,
    "pred": "2",
    "home_pred_score": 1,
    "away_pred_score": 2,
    "prob_1": 21,
    "prob_x": 23,
    "prob_2": 56,
    "avg_goals": 2.71,
    "kelly": null,
    "game_link": "https://www.forebet.com/en/football/matches/burton-albion-cardiff-city-2327002",
    "preview_link": null,
    "country": "England",
    "league_name": "League One",
    "home_correct_score": 2,
    "away_correct_score": 2,
    "home_ht_score": 1,
    "away_ht_score": 0
  },
  {
    "home_team": "Exeter City",
    "away_team": "Rotherham United",
    "home_draw_odds": 1.25,
    "away_draw_odds": 1.73,
    "home_away_odds": 1.3,
    "date": "31 Jan",
    "time": "17:00",
    "game_url": "https://betway.co.za/event/soccer/england/league-one/exeter-city-rotherham-united?eventId=61493427&fixtureType=highlights",
    "home_win": 1.94,
    "draw": 3.3,
    "away_win": 3.7,
    "home_draw_no_bet": 1.42,
    "away_draw_no_bet": 2.65,
    "total_over_1.5": 1.33,
    "total_under_3.5": 1.24,
    "BTTS_yes": 1.89,
    "BTTS_no": 1.82,
    "home_team_over_0.5": 1.23,
    "away_team_over_0.5": 1.5,
    "match_confidence": 100.0,
    "match_id": 2327013,
    "pred": "1",
    "home_pred_score": 1,
    "away_pred_score": 0,
    "prob_1": 47,
    "prob_x": 28,
    "prob_2": 25,
    "avg_goals": 1.93,
    "kelly": null,
    "game_link": "https://www.forebet.com/en/football/matches/exeter-city-rotherham-2327013",
    "preview_link": null,
    "country": "England",
    "league_name": "League One",
    "home_correct_score": 0,
    "away_correct_score": 4,
    "home_ht_score": 0,
    "away_ht_score": 1
  },
  {
    "home_team": "Leyton Orient London",
    "away_team": "Port Vale",
    "home_draw_odds": 1.29,
    "away_draw_odds": 1.65,
    "home_away_odds": 1.3,
    "date": "31 Jan",
    "time": "17:00",
    "game_url": "https://betway.co.za/event/soccer/england/league-one/leyton-orient-london-port-vale?eventId=61493429&fixtureType=highlights",
    "home_win": 2.04,
    "draw": 3.3,
    "away_win": 3.35,
    "home_draw_no_bet": 1.5,
    "away_draw_no_bet": 2.42,
    "total_over_1.5": 1.28,
    "total_under_3.5": 1.3,
    "BTTS_yes": 1.76,
    "BTTS_no": 1.96,
    "home_team_over_0.5": null,
    "away_team_over_0.5": 1.41,
    "match_confidence": 100.0,
    "match_id": 2327006,
    "pred": "1",
    "home_pred_score": 2,
    "away_pred_score": 1,
    "prob_1": 55,
    "prob_x": 29,
    "prob_2": 17,
    "avg_goals": 2.65,
    "kelly": 0.12,
    "game_link": "https://www.forebet.com/en/football/matches/leyton-orient-port-vale-2327006",
    "preview_link": null,
    "country": "England",
    "league_name": "League One",
    "home_correct_score": 0,
    "away_correct_score": 1,
    "home_ht_score": 0,
    "away_ht_score": 1
  },
  {
    "home_team": "Luton Town",
    "away_team": "Blackpool FC",
    "home_draw_odds": 1.86,
    "away_draw_odds": 1.84,
    "home_away_odds": 1.17,
    "date": "31 Jan",
    "time": "17:00",
    "game_url": "https://betway.co.za/event/soccer/england/league-one/luton-town-blackpool-fc?eventId=61493431&fixtureType=highlights",
    "home_win": null,
    "draw": null,
    "away_win": null,
    "home_draw_no_bet": null,
    "away_draw_no_bet": null,
    "total_over_1.5": null,
    "total_under_3.5": null,
    "BTTS_yes": null,
    "BTTS_no": null,
    "home_team_over_0.5": 1.16,
    "away_team_over_0.5": 1.58,
    "match_confidence": 100.0,
    "match_id": 2327008,
    "pred": "1",
    "home_pred_score": 3,
    "away_pred_score": 0,
    "prob_1": 53,
    "prob_x": 27,
    "prob_2": 19,
    "avg_goals": 2.84,
    "kelly": null,
    "game_link": "https://www.forebet.com/en/football/matches/luton-town-blackpool-2327008",
    "preview_link": null,
    "country": "England",
    "league_name": "League One",
    "home_correct_score": 1,
    "away_correct_score": 0,
    "home_ht_score": 0,
    "away_ht_score": 0
  },
  {
    "home_team": "Mansfield Town",
    "away_team": "Wycombe Wanderers",
    "home_draw_odds": 1.5,
    "away_draw_odds": 1.38,
    "home_away_odds": 1.32,
    "date": "31 Jan",
    "time": "17:00",
    "game_url": "https://betway.co.za/event/soccer/england/league-one/mansfield-town-wycombe-wanderers?eventId=61493433&fixtureType=highlights",
    "home_win": 2.8,
    "draw": 3.25,
    "away_win": 2.38,
    "home_draw_no_bet": 2.0,
    "away_draw_no_bet": 1.72,
    "total_over_1.5": 1.29,
    "total_under_3.5": 1.29,
    "BTTS_yes": 1.73,
    "BTTS_no": 1.99,
    "home_team_over_0.5": 1.33,
    "away_team_over_0.5": null,
    "match_confidence": 100.0,
    "match_id": 2327009,
    "pred": "2",
    "home_pred_score": 0,
    "away_pred_score": 1,
    "prob_1": 29,
    "prob_x": 33,
    "prob_2": 37,
    "avg_goals": 2.02,
    "kelly": null,
    "game_link": "https://www.forebet.com/en/football/matches/mansfield-wycombe-2327009",
    "preview_link": null,
    "country": "England",
    "league_name": "League One",
    "home_correct_score": 0,
    "away_correct_score": 0,
    "home_ht_score": 0,
    "away_ht_score": 0
  },
  {
    "home_team": "Peterborough United",
    "away_team": "Huddersfield",
    "home_draw_odds": 1.65,
    "away_draw_odds": 2.11,
    "home_away_odds": 1.54,
    "date": "31 Jan",
    "time": "17:00",
    "game_url": "https://betway.co.za/event/soccer/england/league-one/peterborough-united-huddersfield?eventId=61493437&fixtureType=highlights",
    "home_win": null,
    "draw": null,
    "away_win": null,
    "home_draw_no_bet": null,
    "away_draw_no_bet": null,
    "total_over_1.5": null,
    "total_under_3.5": null,
    "BTTS_yes": null,
    "BTTS_no": null,
    "home_team_over_0.5": 1.31,
    "away_team_over_0.5": 1.24,
    "match_confidence": 100.0,
    "match_id": 2327007,
    "pred": "2",
    "home_pred_score": 1,
    "away_pred_score": 2,
    "prob_1": 35,
    "prob_x": 29,
    "prob_2": 36,
    "avg_goals": 2.75,
    "kelly": null,
    "game_link": "https://www.forebet.com/en/football/matches/peterborough-huddersfield-2327007",
    "preview_link": null,
    "country": "England",
    "league_name": "League One",
    "home_correct_score": 2,
    "away_correct_score": 3,
    "home_ht_score": 0,
    "away_ht_score": 1
  },
  {
    "home_team": "Stockport County FC",
    "away_team": "Plymouth Argyle",
    "home_draw_odds": 1.22,
    "away_draw_odds": 1.83,
    "home_away_odds": 1.27,
    "date": "31 Jan",
    "time": "17:00",
    "game_url": "https://betway.co.za/event/soccer/england/league-one/stockport-county-fc-plymouth-argyle?eventId=61493439&fixtureType=highlights",
    "home_win": 1.8,
    "draw": 3.5,
    "away_win": 4.0,
    "home_draw_no_bet": 1.36,
    "away_draw_no_bet": 2.9,
    "total_over_1.5": 1.23,
    "total_under_3.5": 1.37,
    "BTTS_yes": 1.7,
    "BTTS_no": 2.03,
    "home_team_over_0.5": 1.16,
    "away_team_over_0.5": 1.43,
    "match_confidence": 100.0,
    "match_id": 2327004,
    "pred": "2",
    "home_pred_score": 1,
    "away_pred_score": 2,
    "prob_1": 32,
    "prob_x": 23,
    "prob_2": 46,
    "avg_goals": 2.88,
    "kelly": 0.26,
    "game_link": "https://www.forebet.com/en/football/matches/stockport-county-plymouth-argyle-2327004",
    "preview_link": null,
    "country": "England",
    "league_name": "League One",
    "home_correct_score": 2,
    "away_correct_score": 1,
    "home_ht_score": 0,
    "away_ht_score": 1
  },
  {
    "home_team": "Wigan Athletic",
    "away_team": "Lincoln City",
    "home_draw_odds": 1.61,
    "away_draw_odds": 1.31,
    "home_away_odds": 1.3,
    "date": "31 Jan",
    "time": "17:00",
    "game_url": "https://betway.co.za/event/soccer/england/league-one/wigan-athletic-lincoln-city?eventId=61493441&fixtureType=highlights",
    "home_win": 3.15,
    "draw": 3.25,
    "away_win": 2.15,
    "home_draw_no_bet": 2.3,
    "away_draw_no_bet": 1.55,
    "total_over_1.5": 1.31,
    "total_under_3.5": 1.27,
    "BTTS_yes": 1.8,
    "BTTS_no": 1.9,
    "home_team_over_0.5": 1.41,
    "away_team_over_0.5": 1.25,
    "match_confidence": 100.0,
    "match_id": 2327012,
    "pred": "2",
    "home_pred_score": 0,
    "away_pred_score": 1,
    "prob_1": 19,
    "prob_x": 30,
    "prob_2": 50,
    "avg_goals": 1.85,
    "kelly": 0.14,
    "game_link": "https://www.forebet.com/en/football/matches/wigan-athletic-lincoln-city-2327012",
    "preview_link": null,
    "country": "England",
    "league_name": "League One",
    "home_correct_score": 0,
    "away_correct_score": 1,
    "home_ht_score": 0,
    "away_ht_score": 1
  },
  {
    "home_team": "Boreham Wood FC",
    "away_team": "Boston United FC",
    "home_draw_odds": 1.1,
    "away_draw_odds": 2.65,
    "home_away_odds": 1.16,
    "date": "31 Jan",
    "time": "17:00",
    "game_url": "https://betway.co.za/event/soccer/england/national-league/boreham-wood-fc-boston-united-fc?eventId=61915844&fixtureType=highlights",
    "home_win": 1.35,
    "draw": 4.6,
    "away_win": 7.0,
    "home_draw_no_bet": null,
    "away_draw_no_bet": null,
    "total_over_1.5": 1.16,
    "total_under_3.5": 1.5,
    "BTTS_yes": 1.79,
    "BTTS_no": 1.85,
    "home_team_over_0.5": null,
    "away_team_over_0.5": 1.63,
    "match_confidence": 100.0,
    "match_id": 2339734,
    "pred": "1",
    "home_pred_score": 1,
    "away_pred_score": 0,
    "prob_1": 65,
    "prob_x": 23,
    "prob_2": 12,
    "avg_goals": 1.88,
    "kelly": null,
    "game_link": "https://www.forebet.com/en/football/matches/boreham-wood-boston-united-2339734",
    "preview_link": null,
    "country": "England",
    "league_name": "National League",
    "home_correct_score": 1,
    "away_correct_score": 2,
    "home_ht_score": 1,
    "away_ht_score": 0
  },
  {
    "home_team": "Braintree Town FC",
    "away_team": "Eastleigh FC",
    "home_draw_odds": 1.46,
    "away_draw_odds": 1.43,
    "home_away_odds": 1.3,
    "date": "31 Jan",
    "time": "17:00",
    "game_url": "https://betway.co.za/event/soccer/england/national-league/braintree-town-fc-eastleigh-fc?eventId=61915846&fixtureType=highlights",
    "home_win": 2.6,
    "draw": 3.25,
    "away_win": 2.47,
    "home_draw_no_bet": null,
    "away_draw_no_bet": null,
    "total_over_1.5": 1.27,
    "total_under_3.5": 1.3,
    "BTTS_yes": 1.69,
    "BTTS_no": 1.97,
    "home_team_over_0.5": 1.29,
    "away_team_over_0.5": 1.27,
    "match_confidence": 100.0,
    "match_id": 2339731,
    "pred": "1",
    "home_pred_score": 2,
    "away_pred_score": 1,
    "prob_1": 36,
    "prob_x": 35,
    "prob_2": 29,
    "avg_goals": 2.52,
    "kelly": null,
    "game_link": "https://www.forebet.com/en/football/matches/braintree-town-eastleigh-2339731",
    "preview_link": null,
    "country": "England",
    "league_name": "National League",
    "home_correct_score": 2,
    "away_correct_score": 1,
    "home_ht_score": 1,
    "away_ht_score": 0
  },
  {
    "home_team": "Carlisle United",
    "away_team": "Altrincham FC",
    "home_draw_odds": 1.15,
    "away_draw_odds": 2.2,
    "home_away_odds": 1.2,
    "date": "31 Jan",
    "time": "17:00",
    "game_url": "https://betway.co.za/event/soccer/england/national-league/carlisle-united-altrincham-fc?eventId=61915848&fixtureType=highlights",
    "home_win": 1.52,
    "draw": 4.1,
    "away_win": 5.0,
    "home_draw_no_bet": null,
    "away_draw_no_bet": null,
    "total_over_1.5": 1.18,
    "total_under_3.5": 1.46,
    "BTTS_yes": 1.67,
    "BTTS_no": 1.99,
    "home_team_over_0.5": 1.1,
    "away_team_over_0.5": 1.48,
    "match_confidence": 95.45,
    "match_id": 2339730,
    "pred": "1",
    "home_pred_score": 2,
    "away_pred_score": 1,
    "prob_1": 64,
    "prob_x": 22,
    "prob_2": 14,
    "avg_goals": 2.5,
    "kelly": null,
    "game_link": "https://www.forebet.com/en/football/matches/carlisle-utd-altrincham-2339730",
    "preview_link": null,
    "country": "England",
    "league_name": "National League",
    "home_correct_score": 3,
    "away_correct_score": 1,
    "home_ht_score": 3,
    "away_ht_score": 0
  },
  {
    "home_team": "Hartlepool United",
    "away_team": "Aldershot Town FC",
    "home_draw_odds": 1.3,
    "away_draw_odds": 1.72,
    "home_away_odds": 1.26,
    "date": "31 Jan",
    "time": "17:00",
    "game_url": "https://betway.co.za/event/soccer/england/national-league/hartlepool-united-aldershot-town-fc?eventId=61915854&fixtureType=highlights",
    "home_win": 1.94,
    "draw": 3.6,
    "away_win": 3.25,
    "home_draw_no_bet": null,
    "away_draw_no_bet": null,
    "total_over_1.5": 1.15,
    "total_under_3.5": 1.52,
    "BTTS_yes": 1.49,
    "BTTS_no": 2.34,
    "home_team_over_0.5": 1.13,
    "away_team_over_0.5": 1.27,
    "match_confidence": 96.15,
    "match_id": 2339736,
    "pred": "1",
    "home_pred_score": 2,
    "away_pred_score": 0,
    "prob_1": 44,
    "prob_x": 24,
    "prob_2": 31,
    "avg_goals": 2.43,
    "kelly": null,
    "game_link": "https://www.forebet.com/en/football/matches/hartlepool-utd-aldershot-town-2339736",
    "preview_link": null,
    "country": "England",
    "league_name": "National League",
    "home_correct_score": 0,
    "away_correct_score": 3,
    "home_ht_score": 0,
    "away_ht_score": 1
  },
  {
    "home_team": "Solihull Moors FC",
    "away_team": "York City FC",
    "home_draw_odds": 1.91,
    "away_draw_odds": 1.22,
    "home_away_odds": 1.24,
    "date": "31 Jan",
    "time": "17:00",
    "game_url": "https://betway.co.za/event/soccer/england/national-league/solihull-moors-fc-york-city-fc?eventId=61915856&fixtureType=highlights",
    "home_win": 3.9,
    "draw": 3.8,
    "away_win": 1.72,
    "home_draw_no_bet": null,
    "away_draw_no_bet": null,
    "total_over_1.5": 1.13,
    "total_under_3.5": 1.59,
    "BTTS_yes": 1.48,
    "BTTS_no": 2.37,
    "home_team_over_0.5": 1.31,
    "away_team_over_0.5": 1.1,
    "match_confidence": 100.0,
    "match_id": 2339732,
    "pred": "2",
    "home_pred_score": 2,
    "away_pred_score": 3,
    "prob_1": 18,
    "prob_x": 29,
    "prob_2": 53,
    "avg_goals": 2.69,
    "kelly": null,
    "game_link": "https://www.forebet.com/en/football/matches/solihull-moors-york-city-2339732",
    "preview_link": null,
    "country": "England",
    "league_name": "National League",
    "home_correct_score": 0,
    "away_correct_score": 2,
    "home_ht_score": 0,
    "away_ht_score": 0
  },
  {
    "home_team": "Sutton United",
    "away_team": "Brackley Town FC",
    "home_draw_odds": 1.3,
    "away_draw_odds": 1.63,
    "home_away_odds": 1.3,
    "date": "31 Jan",
    "time": "17:00",
    "game_url": "https://betway.co.za/event/soccer/england/national-league/sutton-united-brackley-town-fc?eventId=61915860&fixtureType=highlights",
    "home_win": 2.07,
    "draw": 3.25,
    "away_win": 3.25,
    "home_draw_no_bet": null,
    "away_draw_no_bet": null,
    "total_over_1.5": 1.26,
    "total_under_3.5": 1.31,
    "BTTS_yes": 1.69,
    "BTTS_no": 1.96,
    "home_team_over_0.5": 1.21,
    "away_team_over_0.5": 1.37,
    "match_confidence": 100.0,
    "match_id": 2339726,
    "pred": "2",
    "home_pred_score": 0,
    "away_pred_score": 1,
    "prob_1": 19,
    "prob_x": 37,
    "prob_2": 44,
    "avg_goals": 2.17,
    "kelly": 0.2,
    "game_link": "https://www.forebet.com/en/football/matches/sutton-united-brackley-town-2339726",
    "preview_link": null,
    "country": "England",
    "league_name": "National League",
    "home_correct_score": 1,
    "away_correct_score": 1,
    "home_ht_score": 1,
    "away_ht_score": 1
  },
  {
    "home_team": "Bristol Rovers",
    "away_team": "Newport County",
    "home_draw_odds": 1.2,
    "away_draw_odds": 1.91,
    "home_away_odds": 1.26,
    "date": "31 Jan",
    "time": "14:30",
    "game_url": "https://betway.co.za/event/soccer/england/league-two/bristol-rovers-newport-county?eventId=61494657&fixtureType=highlights",
    "home_win": 1.72,
    "draw": 3.6,
    "away_win": 4.3,
    "home_draw_no_bet": 1.31,
    "away_draw_no_bet": 3.15,
    "total_over_1.5": 1.24,
    "total_under_3.5": 1.35,
    "BTTS_yes": 1.76,
    "BTTS_no": 1.96,
    "home_team_over_0.5": 1.16,
    "away_team_over_0.5": 1.49,
    "match_confidence": 100.0,
    "match_id": 2330160,
    "pred": "1",
    "home_pred_score": 2,
    "away_pred_score": 0,
    "prob_1": 40,
    "prob_x": 25,
    "prob_2": 34,
    "avg_goals": 2.31,
    "kelly": null,
    "game_link": "https://www.forebet.com/en/football/matches/bristol-rovers-newport-county-2330160",
    "preview_link": null,
    "country": "England",
    "league_name": "League Two",
    "home_correct_score": 3,
    "away_correct_score": 0,
    "home_ht_score": 2,
    "away_ht_score": 0
  },
  {
    "home_team": "Grimsby Town",
    "away_team": "Milton Keynes Dons",
    "home_draw_odds": 1.45,
    "away_draw_odds": 1.45,
    "home_away_odds": 1.3,
    "date": "31 Jan",
    "time": "14:30",
    "game_url": "https://betway.co.za/event/soccer/england/league-two/grimsby-town-milton-keynes-dons?eventId=61494669&fixtureType=highlights",
    "home_win": 2.55,
    "draw": 3.35,
    "away_win": 2.5,
    "home_draw_no_bet": 1.86,
    "away_draw_no_bet": 1.85,
    "total_over_1.5": 1.26,
    "total_under_3.5": 1.32,
    "BTTS_yes": 1.69,
    "BTTS_no": 2.04,
    "home_team_over_0.5": 1.29,
    "away_team_over_0.5": 1.29,
    "match_confidence": 100.0,
    "match_id": 2330157,
    "pred": "2",
    "home_pred_score": 0,
    "away_pred_score": 1,
    "prob_1": 24,
    "prob_x": 32,
    "prob_2": 44,
    "avg_goals": 1.58,
    "kelly": 0.07,
    "game_link": "https://www.forebet.com/en/football/matches/grimsby-town-milton-keynes-dons-2330157",
    "preview_link": null,
    "country": "England",
    "league_name": "League Two",
    "home_correct_score": 2,
    "away_correct_score": 2,
    "home_ht_score": 0,
    "away_ht_score": 2
  },
  {
    "home_team": "Accrington Stanley",
    "away_team": "Cheltenham Town",
    "home_draw_odds": 1.25,
    "away_draw_odds": 1.72,
    "home_away_odds": 1.31,
    "date": "31 Jan",
    "time": "17:00",
    "game_url": "https://betway.co.za/event/soccer/england/league-two/accrington-stanley-cheltenham-town?eventId=61494655&fixtureType=highlights",
    "home_win": 1.94,
    "draw": 3.25,
    "away_win": 3.75,
    "home_draw_no_bet": 1.42,
    "away_draw_no_bet": 2.65,
    "total_over_1.5": 1.34,
    "total_under_3.5": 1.23,
    "BTTS_yes": 1.91,
    "BTTS_no": 1.8,
    "home_team_over_0.5": 1.24,
    "away_team_over_0.5": 1.52,
    "match_confidence": 100.0,
    "match_id": 2330154,
    "pred": "1",
    "home_pred_score": 1,
    "away_pred_score": 0,
    "prob_1": 44,
    "prob_x": 30,
    "prob_2": 26,
    "avg_goals": 1.96,
    "kelly": null,
    "game_link": "https://www.forebet.com/en/football/matches/accrington-stanley-cheltenham-2330154",
    "preview_link": null,
    "country": "England",
    "league_name": "League Two",
    "home_correct_score": 3,
    "away_correct_score": 1,
    "home_ht_score": 2,
    "away_ht_score": 0
  },
  {
    "home_team": "Chesterfield FC",
    "away_team": "Walsall FC",
    "home_draw_odds": 1.32,
    "away_draw_odds": 1.58,
    "home_away_odds": 1.32,
    "date": "31 Jan",
    "time": "17:00",
    "game_url": "https://betway.co.za/event/soccer/england/league-two/chesterfield-fc-walsall-fc?eventId=61494659&fixtureType=highlights",
    "home_win": 2.18,
    "draw": 3.2,
    "away_win": 3.15,
    "home_draw_no_bet": 1.58,
    "away_draw_no_bet": 2.24,
    "total_over_1.5": 1.32,
    "total_under_3.5": 1.26,
    "BTTS_yes": 1.81,
    "BTTS_no": 1.9,
    "home_team_over_0.5": 1.26,
    "away_team_over_0.5": 1.41,
    "match_confidence": 100.0,
    "match_id": 2330161,
    "pred": "X",
    "home_pred_score": 1,
    "away_pred_score": 1,
    "prob_1": 22,
    "prob_x": 47,
    "prob_2": 31,
    "avg_goals": 1.8,
    "kelly": 0.22,
    "game_link": "https://www.forebet.com/en/football/matches/chesterfield-walsall-fc-2330161",
    "preview_link": null,
    "country": "England",
    "league_name": "League Two",
    "home_correct_score": 2,
    "away_correct_score": 2,
    "home_ht_score": 2,
    "away_ht_score": 1
  },
  {
    "home_team": "Crawley Town",
    "away_team": "Harrogate Town",
    "home_draw_odds": 1.17,
    "away_draw_odds": 2.1,
    "home_away_odds": 1.22,
    "date": "31 Jan",
    "time": "17:00",
    "game_url": "https://betway.co.za/event/soccer/england/league-two/crawley-town-harrogate-town?eventId=61494661&fixtureType=highlights",
    "home_win": 1.59,
    "draw": 3.9,
    "away_win": 4.9,
    "home_draw_no_bet": 1.24,
    "away_draw_no_bet": 3.6,
    "total_over_1.5": 1.2,
    "total_under_3.5": 1.43,
    "BTTS_yes": 1.71,
    "BTTS_no": 2.01,
    "home_team_over_0.5": 1.12,
    "away_team_over_0.5": 1.5,
    "match_confidence": 100.0,
    "match_id": 2330151,
    "pred": "1",
    "home_pred_score": 2,
    "away_pred_score": 0,
    "prob_1": 47,
    "prob_x": 38,
    "prob_2": 15,
    "avg_goals": 2.14,
    "kelly": null,
    "game_link": "https://www.forebet.com/en/football/matches/crawley-town-harrogate-town-2330151",
    "preview_link": null,
    "country": "England",
    "league_name": "League Two",
    "home_correct_score": 2,
    "away_correct_score": 0,
    "home_ht_score": 1,
    "away_ht_score": 0
  },
  {
    "home_team": "Crewe Alexandra",
    "away_team": "Colchester United",
    "home_draw_odds": 1.45,
    "away_draw_odds": 1.44,
    "home_away_odds": 1.31,
    "date": "31 Jan",
    "time": "17:00",
    "game_url": "https://betway.co.za/event/soccer/england/league-two/crewe-alexandra-colchester-united?eventId=61494663&fixtureType=highlights",
    "home_win": 2.55,
    "draw": 3.3,
    "away_win": 2.5,
    "home_draw_no_bet": 1.87,
    "away_draw_no_bet": 1.83,
    "total_over_1.5": 1.26,
    "total_under_3.5": 1.32,
    "BTTS_yes": 1.69,
    "BTTS_no": 2.05,
    "home_team_over_0.5": 1.29,
    "away_team_over_0.5": 1.28,
    "match_confidence": 96.15,
    "match_id": 2330162,
    "pred": "1",
    "home_pred_score": 2,
    "away_pred_score": 0,
    "prob_1": 34,
    "prob_x": 34,
    "prob_2": 32,
    "avg_goals": 2.19,
    "kelly": null,
    "game_link": "https://www.forebet.com/en/football/matches/crewe-alexandra-colchester-utd-2330162",
    "preview_link": null,
    "country": "England",
    "league_name": "League Two",
    "home_correct_score": 1,
    "away_correct_score": 0,
    "home_ht_score": 0,
    "away_ht_score": 0
  },
  {
    "home_team": "Fleetwood Town",
    "away_team": "Notts County",
    "home_draw_odds": 1.6,
    "away_draw_odds": 1.33,
    "home_away_odds": 1.3,
    "date": "31 Jan",
    "time": "17:00",
    "game_url": "https://betway.co.za/event/soccer/england/league-two/fleetwood-town-notts-county?eventId=61494665&fixtureType=highlights",
    "home_win": 3.1,
    "draw": 3.3,
    "away_win": 2.15,
    "home_draw_no_bet": 2.25,
    "away_draw_no_bet": 1.57,
    "total_over_1.5": 1.26,
    "total_under_3.5": 1.32,
    "BTTS_yes": 1.71,
    "BTTS_no": 2.02,
    "home_team_over_0.5": 1.36,
    "away_team_over_0.5": 1.23,
    "match_confidence": 100.0,
    "match_id": 2330152,
    "pred": "2",
    "home_pred_score": 0,
    "away_pred_score": 2,
    "prob_1": 23,
    "prob_x": 27,
    "prob_2": 50,
    "avg_goals": 2.25,
    "kelly": 0.16,
    "game_link": "https://www.forebet.com/en/football/matches/fleetwood-town-notts-county-2330152",
    "preview_link": null,
    "country": "England",
    "league_name": "League Two",
    "home_correct_score": 1,
    "away_correct_score": 2,
    "home_ht_score": 0,
    "away_ht_score": 1
  },
  {
    "home_team": "Gillingham FC",
    "away_team": "Bromley FC",
    "home_draw_odds": 1.44,
    "away_draw_odds": 1.43,
    "home_away_odds": 1.32,
    "date": "31 Jan",
    "time": "17:00",
    "game_url": "https://betway.co.za/event/soccer/england/league-two/gillingham-fc-bromley-fc?eventId=61494667&fixtureType=highlights",
    "home_win": 2.6,
    "draw": 3.15,
    "away_win": 2.55,
    "home_draw_no_bet": 1.87,
    "away_draw_no_bet": 1.83,
    "total_over_1.5": 1.34,
    "total_under_3.5": 1.24,
    "BTTS_yes": 1.83,
    "BTTS_no": 1.87,
    "home_team_over_0.5": 1.35,
    "away_team_over_0.5": 1.34,
    "match_confidence": 100.0,
    "match_id": 2330158,
    "pred": "2",
    "home_pred_score": 1,
    "away_pred_score": 2,
    "prob_1": 20,
    "prob_x": 36,
    "prob_2": 44,
    "avg_goals": 2.75,
    "kelly": 0.04,
    "game_link": "https://www.forebet.com/en/football/matches/gillingham-bromley-fc-2330158",
    "preview_link": null,
    "country": "England",
    "league_name": "League Two",
    "home_correct_score": 1,
    "away_correct_score": 4,
    "home_ht_score": 1,
    "away_ht_score": 3
  },
  {
    "home_team": "Oldham Athletic",
    "away_team": "Cambridge United",
    "home_draw_odds": 1.42,
    "away_draw_odds": 1.42,
    "home_away_odds": 1.35,
    "date": "31 Jan",
    "time": "17:00",
    "game_url": "https://betway.co.za/event/soccer/england/league-two/oldham-athletic-cambridge-united?eventId=61494671&fixtureType=highlights",
    "home_win": 2.65,
    "draw": 3.0,
    "away_win": 2.65,
    "home_draw_no_bet": 1.85,
    "away_draw_no_bet": 1.86,
    "total_over_1.5": 1.43,
    "total_under_3.5": 1.17,
    "BTTS_yes": 2.0,
    "BTTS_no": 1.72,
    "home_team_over_0.5": 1.4,
    "away_team_over_0.5": 1.41,
    "match_confidence": 95.83,
    "match_id": 2330156,
    "pred": "2",
    "home_pred_score": 0,
    "away_pred_score": 2,
    "prob_1": 22,
    "prob_x": 30,
    "prob_2": 48,
    "avg_goals": 2.3,
    "kelly": 0.17,
    "game_link": "https://www.forebet.com/en/football/matches/oldham-athletic-cambridge-utd-2330156",
    "preview_link": null,
    "country": "England",
    "league_name": "League Two",
    "home_correct_score": 0,
    "away_correct_score": 3,
    "home_ht_score": 0,
    "away_ht_score": 0
  },
  {
    "home_team": "Shrewsbury Town",
    "away_team": "Barnet FC",
    "home_draw_odds": 1.8,
    "away_draw_odds": 1.23,
    "home_away_odds": 1.28,
    "date": "31 Jan",
    "time": "17:00",
    "game_url": "https://betway.co.za/event/soccer/england/league-two/shrewsbury-town-barnet-fc?eventId=61494673&fixtureType=highlights",
    "home_win": 3.9,
    "draw": 3.45,
    "away_win": 1.84,
    "home_draw_no_bet": 2.85,
    "away_draw_no_bet": 1.38,
    "total_over_1.5": 1.26,
    "total_under_3.5": 1.33,
    "BTTS_yes": 1.76,
    "BTTS_no": 1.96,
    "home_team_over_0.5": 1.45,
    "away_team_over_0.5": 1.18,
    "match_confidence": 100.0,
    "match_id": 2330153,
    "pred": "2",
    "home_pred_score": 0,
    "away_pred_score": 2,
    "prob_1": 27,
    "prob_x": 30,
    "prob_2": 44,
    "avg_goals": 1.55,
    "kelly": null,
    "game_link": "https://www.forebet.com/en/football/matches/shrewsbury-barnet-2330153",
    "preview_link": null,
    "country": "England",
    "league_name": "League Two",
    "home_correct_score": 0,
    "away_correct_score": 0,
    "home_ht_score": 0,
    "away_ht_score": 0
  },
  {
    "home_team": "Swindon Town",
    "away_team": "Barrow AFC",
    "home_draw_odds": 1.2,
    "away_draw_odds": 1.93,
    "home_away_odds": 1.26,
    "date": "31 Jan",
    "time": "17:00",
    "game_url": "https://betway.co.za/event/soccer/england/league-two/swindon-town-barrow-afc?eventId=61494675&fixtureType=highlights",
    "home_win": 1.71,
    "draw": 3.6,
    "away_win": 4.4,
    "home_draw_no_bet": 1.3,
    "away_draw_no_bet": 3.2,
    "total_over_1.5": 1.25,
    "total_under_3.5": 1.34,
    "BTTS_yes": 1.78,
    "BTTS_no": 1.93,
    "home_team_over_0.5": 1.16,
    "away_team_over_0.5": 1.5,
    "match_confidence": 100.0,
    "match_id": 2330159,
    "pred": "1",
    "home_pred_score": 1,
    "away_pred_score": 0,
    "prob_1": 62,
    "prob_x": 22,
    "prob_2": 17,
    "avg_goals": 2.18,
    "kelly": 0.04,
    "game_link": "https://www.forebet.com/en/football/matches/swindon-town-barrow-afc-2330159",
    "preview_link": null,
    "country": "England",
    "league_name": "League Two",
    "home_correct_score": 3,
    "away_correct_score": 1,
    "home_ht_score": 1,
    "away_ht_score": 1
  },
  {
    "home_team": "Tranmere Rovers FC",
    "away_team": "Salford City",
    "home_draw_odds": 1.71,
    "away_draw_odds": 1.29,
    "home_away_odds": 1.27,
    "date": "31 Jan",
    "time": "17:00",
    "game_url": "https://betway.co.za/event/soccer/england/league-two/tranmere-rovers-fc-salford-city?eventId=61494677&fixtureType=highlights",
    "home_win": 3.35,
    "draw": 3.5,
    "away_win": 1.97,
    "home_draw_no_bet": 2.49,
    "away_draw_no_bet": 1.47,
    "total_over_1.5": 1.21,
    "total_under_3.5": 1.41,
    "BTTS_yes": 1.61,
    "BTTS_no": 2.18,
    "home_team_over_0.5": 1.34,
    "away_team_over_0.5": 1.17,
    "match_confidence": 100.0,
    "match_id": 2330155,
    "pred": "2",
    "home_pred_score": 1,
    "away_pred_score": 2,
    "prob_1": 27,
    "prob_x": 23,
    "prob_2": 50,
    "avg_goals": 2.64,
    "kelly": 0.05,
    "game_link": "https://www.forebet.com/en/football/matches/tranmere-rovers-salford-city-2330155",
    "preview_link": null,
    "country": "England",
    "league_name": "League Two",
    "home_correct_score": 0,
    "away_correct_score": 2,
    "home_ht_score": 0,
    "away_ht_score": 0
  },
  {
    "home_team": "Real Oviedo",
    "away_team": "Girona FC",
    "home_draw_odds": 1.45,
    "away_draw_odds": 1.47,
    "home_away_odds": 1.37,
    "date": "31 Jan",
    "time": "15:00",
    "game_url": "https://betway.co.za/event/soccer/spain/la-liga/real-oviedo-girona-fc?eventId=61624374&fixtureType=highlights",
    "home_win": 2.65,
    "draw": 3.1,
    "away_win": 2.8,
    "home_draw_no_bet": 1.87,
    "away_draw_no_bet": 1.91,
    "total_over_1.5": 1.4,
    "total_under_3.5": 1.23,
    "BTTS_yes": 1.92,
    "BTTS_no": 1.86,
    "home_team_over_0.5": 1.38,
    "away_team_over_0.5": 1.39,
    "match_confidence": 100.0,
    "match_id": 2316642,
    "pred": "2",
    "home_pred_score": 0,
    "away_pred_score": 2,
    "prob_1": 20,
    "prob_x": 34,
    "prob_2": 46,
    "avg_goals": 2.35,
    "kelly": 0.16,
    "game_link": "https://www.forebet.com/en/football/matches/real-oviedo-girona-2316642",
    "preview_link": "https://www.forebet.com/en/football-match-previews/25417-girona-look-for-top-half-push-against-winless-real-oviedo",
    "country": "Spain",
    "league_name": "Primera Division",
    "home_correct_score": 1,
    "away_correct_score": 0,
    "home_ht_score": 0,
    "away_ht_score": 0
  },
  {
    "home_team": "CA Osasuna",
    "away_team": "Villarreal CF",
    "home_draw_odds": 1.54,
    "away_draw_odds": 1.42,
    "home_away_odds": 1.34,
    "date": "31 Jan",
    "time": "17:15",
    "game_url": "https://betway.co.za/event/soccer/spain/la-liga/ca-osasuna-villarreal-cf?eventId=61624364&fixtureType=highlights",
    "home_win": 2.8,
    "draw": 3.3,
    "away_win": 2.47,
    "home_draw_no_bet": 2.04,
    "away_draw_no_bet": 1.75,
    "total_over_1.5": 1.27,
    "total_under_3.5": 1.36,
    "BTTS_yes": 1.7,
    "BTTS_no": 2.13,
    "home_team_over_0.5": 1.32,
    "away_team_over_0.5": 1.27,
    "match_confidence": 100.0,
    "match_id": 2316639,
    "pred": "1",
    "home_pred_score": null,
    "away_pred_score": null,
    "prob_1": null,
    "prob_x": null,
    "prob_2": null,
    "avg_goals": null,
    "kelly": null,
    "game_link": "https://www.forebet.com/en/football/matches/osasuna-villarreal-2316639",
    "preview_link": null,
    "country": "Spain",
    "league_name": "Primera Division",
    "home_correct_score": 2,
    "away_correct_score": 2,
    "home_ht_score": 2,
    "away_ht_score": 1
  },
  {
    "home_team": "Levante UD",
    "away_team": "Atletico Madrid",
    "home_draw_odds": 2.27,
    "away_draw_odds": 1.18,
    "home_away_odds": 1.24,
    "date": "31 Jan",
    "time": "19:30",
    "game_url": "https://betway.co.za/event/soccer/spain/la-liga/levante-ud-atletico-madrid?eventId=61624368&fixtureType=highlights",
    "home_win": 5.2,
    "draw": 4.1,
    "away_win": 1.61,
    "home_draw_no_bet": 3.9,
    "away_draw_no_bet": 1.24,
    "total_over_1.5": 1.24,
    "total_under_3.5": 1.42,
    "BTTS_yes": 1.81,
    "BTTS_no": 1.97,
    "home_team_over_0.5": 1.57,
    "away_team_over_0.5": 1.13,
    "match_confidence": 96.67,
    "match_id": 2316645,
    "pred": "2",
    "home_pred_score": null,
    "away_pred_score": null,
    "prob_1": null,
    "prob_x": null,
    "prob_2": null,
    "avg_goals": null,
    "kelly": null,
    "game_link": "https://www.forebet.com/en/football/matches/levante-atlético-madrid-2316645",
    "preview_link": null,
    "country": "Spain",
    "league_name": "Primera Division",
    "home_correct_score": 0,
    "away_correct_score": 0,
    "home_ht_score": 0,
    "away_ht_score": 0
  },
  {
    "home_team": "Albacete Balompie",
    "away_team": "Real Zaragoza",
    "home_draw_odds": 1.27,
    "away_draw_odds": 1.7,
    "home_away_odds": 1.29,
    "date": "31 Jan",
    "time": "17:15",
    "game_url": "https://betway.co.za/event/soccer/spain/laliga-2/albacete-balompie-real-zaragoza?eventId=61623538&fixtureType=highlights",
    "home_win": 1.97,
    "draw": 3.35,
    "away_win": 3.55,
    "home_draw_no_bet": 1.45,
    "away_draw_no_bet": 2.55,
    "total_over_1.5": 1.29,
    "total_under_3.5": 1.28,
    "BTTS_yes": 1.79,
    "BTTS_no": 1.91,
    "home_team_over_0.5": 1.22,
    "away_team_over_0.5": 1.44,
    "match_confidence": 100.0,
    "match_id": 2353005,
    "pred": "X",
    "home_pred_score": 1,
    "away_pred_score": 1,
    "prob_1": 37,
    "prob_x": 39,
    "prob_2": 25,
    "avg_goals": 2.4,
    "kelly": 0.14,
    "game_link": "https://www.forebet.com/en/football/matches/albacete-balompie-real-zaragoza-2353005",
    "preview_link": null,
    "country": "Spain",
    "league_name": "Segunda Division",
    "home_correct_score": 2,
    "away_correct_score": 0,
    "home_ht_score": 1,
    "away_ht_score": 0
  },
  {
    "home_team": "Burgos CF",
    "away_team": "CD Leganes",
    "home_draw_odds": 1.3,
    "away_draw_odds": 1.53,
    "home_away_odds": 1.38,
    "date": "31 Jan",
    "time": "17:15",
    "game_url": "https://betway.co.za/event/soccer/spain/laliga-2/burgos-cf-cd-leganes?eventId=61623540&fixtureType=highlights",
    "home_win": 2.29,
    "draw": 2.85,
    "away_win": 3.3,
    "home_draw_no_bet": 1.58,
    "away_draw_no_bet": 2.25,
    "total_over_1.5": 1.55,
    "total_under_3.5": 1.12,
    "BTTS_yes": 2.24,
    "BTTS_no": 1.58,
    "home_team_over_0.5": 1.4,
    "away_team_over_0.5": 1.6,
    "match_confidence": 100.0,
    "match_id": 2353013,
    "pred": "X",
    "home_pred_score": 0,
    "away_pred_score": 0,
    "prob_1": 31,
    "prob_x": 39,
    "prob_2": 30,
    "avg_goals": 1.72,
    "kelly": 0.07,
    "game_link": "https://www.forebet.com/en/football/matches/burgos-cf-leganes-2353013",
    "preview_link": null,
    "country": "Spain",
    "league_name": "Segunda Division",
    "home_correct_score": 2,
    "away_correct_score": 1,
    "home_ht_score": 0,
    "away_ht_score": 0
  },
  {
    "home_team": "Cultural Leonesa",
    "away_team": "RC Deportivo La Coruna",
    "home_draw_odds": 1.52,
    "away_draw_odds": 1.36,
    "home_away_odds": 1.32,
    "date": "31 Jan",
    "time": "19:30",
    "game_url": "https://betway.co.za/event/soccer/spain/laliga-2/cultural-leonesa-rc-deportivo-la-coruna?eventId=61623552&fixtureType=highlights",
    "home_win": 2.9,
    "draw": 3.2,
    "away_win": 2.32,
    "home_draw_no_bet": 2.08,
    "away_draw_no_bet": 1.67,
    "total_over_1.5": 1.29,
    "total_under_3.5": 1.29,
    "BTTS_yes": 1.74,
    "BTTS_no": 1.98,
    "home_team_over_0.5": 1.35,
    "away_team_over_0.5": 1.27,
    "match_confidence": 97.37,
    "match_id": 2353011,
    "pred": "2",
    "home_pred_score": 1,
    "away_pred_score": 2,
    "prob_1": 23,
    "prob_x": 28,
    "prob_2": 49,
    "avg_goals": 2.98,
    "kelly": 0.12,
    "game_link": "https://www.forebet.com/en/football/matches/cultural-leonesa-deportivo-la-coruña-2353011",
    "preview_link": null,
    "country": "Spain",
    "league_name": "Segunda Division",
    "home_correct_score": 0,
    "away_correct_score": 1,
    "home_ht_score": 0,
    "away_ht_score": 0
  },
  {
    "home_team": "Cordoba CF",
    "away_team": "Real Valladolid",
    "home_draw_odds": 1.26,
    "away_draw_odds": 1.7,
    "home_away_odds": 1.3,
    "date": "31 Jan",
    "time": "22:00",
    "game_url": "https://betway.co.za/event/soccer/spain/laliga-2/cordoba-cf-real-valladolid?eventId=61623542&fixtureType=highlights",
    "home_win": 1.97,
    "draw": 3.3,
    "away_win": 3.6,
    "home_draw_no_bet": 1.45,
    "away_draw_no_bet": 2.55,
    "total_over_1.5": 1.29,
    "total_under_3.5": 1.28,
    "BTTS_yes": 1.8,
    "BTTS_no": 1.91,
    "home_team_over_0.5": 1.22,
    "away_team_over_0.5": 1.45,
    "match_confidence": 92.86,
    "match_id": 2353006,
    "pred": "1",
    "home_pred_score": 1,
    "away_pred_score": 0,
    "prob_1": 41,
    "prob_x": 31,
    "prob_2": 28,
    "avg_goals": 2.39,
    "kelly": null,
    "game_link": "https://www.forebet.com/en/football/matches/córdoba-real-valladolid-2353006",
    "preview_link": null,
    "country": "Spain",
    "league_name": "Segunda Division",
    "home_correct_score": 3,
    "away_correct_score": 1,
    "home_ht_score": 1,
    "away_ht_score": 1
  },
  {
    "home_team": "Sevilla Atletico",
    "away_team": "CE Europa",
    "home_draw_odds": 1.38,
    "away_draw_odds": 1.4,
    "home_away_odds": 1.32,
    "date": "31 Jan",
    "time": "15:00",
    "game_url": "https://betway.co.za/event/soccer/spain/primera-federacion/sevilla-atletico-ce-europa?eventId=61687324&fixtureType=highlights",
    "home_win": 2.6,
    "draw": 2.95,
    "away_win": 2.65,
    "home_draw_no_bet": 1.79,
    "away_draw_no_bet": 1.85,
    "total_over_1.5": 1.44,
    "total_under_3.5": 1.16,
    "BTTS_yes": 1.99,
    "BTTS_no": 1.67,
    "home_team_over_0.5": 1.37,
    "away_team_over_0.5": 1.39,
    "match_confidence": 100.0,
    "match_id": 2365148,
    "pred": "X",
    "home_pred_score": 1,
    "away_pred_score": 1,
    "prob_1": 19,
    "prob_x": 56,
    "prob_2": 25,
    "avg_goals": 2.33,
    "kelly": 0.33,
    "game_link": "https://www.forebet.com/en/football/matches/sevilla-atletico-ce-europa-2365148",
    "preview_link": null,
    "country": "Spain",
    "league_name": "Primera Division Rfef",
    "home_correct_score": 0,
    "away_correct_score": 1,
    "home_ht_score": 0,
    "away_ht_score": 0
  },
  {
    "home_team": "Tenerife CD",
    "away_team": "CD Guadalajara",
    "home_draw_odds": 1.06,
    "away_draw_odds": 2.7,
    "home_away_odds": 1.13,
    "date": "31 Jan",
    "time": "17:15",
    "game_url": "https://betway.co.za/event/soccer/spain/primera-federacion/tenerife-cd-cd-guadalajara?eventId=61685428&fixtureType=highlights",
    "home_win": 1.29,
    "draw": 4.6,
    "away_win": 9.4,
    "home_draw_no_bet": 1.07,
    "away_draw_no_bet": 6.0,
    "total_over_1.5": 1.28,
    "total_under_3.5": 1.28,
    "BTTS_yes": 2.41,
    "BTTS_no": 1.46,
    "home_team_over_0.5": 1.09,
    "away_team_over_0.5": 2.09,
    "match_confidence": 94.0,
    "match_id": 2364780,
    "pred": "1",
    "home_pred_score": 3,
    "away_pred_score": 0,
    "prob_1": 70,
    "prob_x": 17,
    "prob_2": 13,
    "avg_goals": 2.5,
    "kelly": null,
    "game_link": "https://www.forebet.com/en/football/matches/tenerife-guadalajara-(esp)-2364780",
    "preview_link": null,
    "country": "Spain",
    "league_name": "Primera Division Rfef",
    "home_correct_score": 4,
    "away_correct_score": 0,
    "home_ht_score": 1,
    "away_ht_score": 0
  },
  {
    "home_team": "Villarreal CF B U23",
    "away_team": "SD Tarazona",
    "home_draw_odds": 2.02,
    "away_draw_odds": 1.82,
    "home_away_odds": 1.16,
    "date": "31 Jan",
    "time": "19:30",
    "game_url": "https://betway.co.za/event/soccer/spain/primera-federacion/villarreal-cf-b-u23-sd-tarazona?eventId=61687322&fixtureType=highlights",
    "home_win": 1.72,
    "draw": 3.3,
    "away_win": 4.6,
    "home_draw_no_bet": 1.27,
    "away_draw_no_bet": 3.2,
    "total_over_1.5": 1.36,
    "total_under_3.5": 1.21,
    "BTTS_yes": 2.02,
    "BTTS_no": 1.65,
    "home_team_over_0.5": null,
    "away_team_over_0.5": 1.62,
    "match_confidence": 97.83,
    "match_id": 2365153,
    "pred": "X",
    "home_pred_score": 1,
    "away_pred_score": 1,
    "prob_1": 26,
    "prob_x": 38,
    "prob_2": 36,
    "avg_goals": 2.2,
    "kelly": 0.05,
    "game_link": "https://www.forebet.com/en/football/matches/villarreal-b-sd-tarazona-2365153",
    "preview_link": null,
    "country": "Spain",
    "league_name": "Primera Division Rfef",
    "home_correct_score": 1,
    "away_correct_score": 1,
    "home_ht_score": 0,
    "away_ht_score": 0
  },
  {
    "home_team": "Real Aviles CF",
    "away_team": "Merida AD",
    "home_draw_odds": 1.33,
    "away_draw_odds": 1.47,
    "home_away_odds": 1.31,
    "date": "31 Jan",
    "time": "22:00",
    "game_url": "https://betway.co.za/event/soccer/spain/primera-federacion/real-aviles-cf-merida-ad?eventId=61685418&fixtureType=highlights",
    "home_win": 2.34,
    "draw": 3.05,
    "away_win": 2.9,
    "home_draw_no_bet": 1.65,
    "away_draw_no_bet": 2.02,
    "total_over_1.5": 1.35,
    "total_under_3.5": 1.22,
    "BTTS_yes": 1.83,
    "BTTS_no": 1.8,
    "home_team_over_0.5": 1.28,
    "away_team_over_0.5": 1.37,
    "match_confidence": 89.9,
    "match_id": 2364779,
    "pred": "2",
    "home_pred_score": 1,
    "away_pred_score": 2,
    "prob_1": 33,
    "prob_x": 24,
    "prob_2": 43,
    "avg_goals": 2.63,
    "kelly": 0.15,
    "game_link": "https://www.forebet.com/en/football/matches/real-avilés-mérida-ad-2364779",
    "preview_link": null,
    "country": "Spain",
    "league_name": "Primera Division Rfef",
    "home_correct_score": 1,
    "away_correct_score": 2,
    "home_ht_score": 0,
    "away_ht_score": 1
  },
  {
    "home_team": "Eintracht Frankfurt",
    "away_team": "Bayer Leverkusen",
    "home_draw_odds": 1.61,
    "away_draw_odds": 1.36,
    "home_away_odds": 1.26,
    "date": "31 Jan",
    "time": "16:30",
    "game_url": "https://betway.co.za/event/soccer/germany/bundesliga/eintracht-frankfurt-bayer-leverkusen?eventId=61513950&fixtureType=highlights",
    "home_win": 2.9,
    "draw": 3.65,
    "away_win": 2.22,
    "home_draw_no_bet": 2.2,
    "away_draw_no_bet": 1.63,
    "total_over_1.5": 1.16,
    "total_under_3.5": 1.59,
    "BTTS_yes": 1.48,
    "BTTS_no": 2.55,
    "home_team_over_0.5": 1.24,
    "away_team_over_0.5": 1.16,
    "match_confidence": 100.0,
    "match_id": 2344073,
    "pred": "2",
    "home_pred_score": null,
    "away_pred_score": null,
    "prob_1": null,
    "prob_x": null,
    "prob_2": null,
    "avg_goals": null,
    "kelly": null,
    "game_link": "https://www.forebet.com/en/football/matches/eintracht-frankfurt-bayer-leverkusen-2344073",
    "preview_link": null,
    "country": "Germany",
    "league_name": "Bundesliga",
    "home_correct_score": 1,
    "away_correct_score": 3,
    "home_ht_score": 0,
    "away_ht_score": 2
  },
  {
    "home_team": "TSG Hoffenheim",
    "away_team": "Union Berlin",
    "home_draw_odds": 1.21,
    "away_draw_odds": 1.92,
    "home_away_odds": 1.25,
    "date": "31 Jan",
    "time": "16:30",
    "game_url": "https://betway.co.za/event/soccer/germany/bundesliga/tsg-hoffenheim-union-berlin?eventId=61513962&fixtureType=highlights",
    "home_win": 1.77,
    "draw": 3.7,
    "away_win": 4.2,
    "home_draw_no_bet": 1.33,
    "away_draw_no_bet": 3.15,
    "total_over_1.5": 1.25,
    "total_under_3.5": 1.38,
    "BTTS_yes": 1.76,
    "BTTS_no": 2.0,
    "home_team_over_0.5": 1.16,
    "away_team_over_0.5": 1.48,
    "match_confidence": 100.0,
    "match_id": 2344070,
    "pred": "X",
    "home_pred_score": 2,
    "away_pred_score": 2,
    "prob_1": 35,
    "prob_x": 37,
    "prob_2": 28,
    "avg_goals": 3.28,
    "kelly": 0.14,
    "game_link": "https://www.forebet.com/en/football/matches/hoffenheim-union-berlin-2344070",
    "preview_link": "https://www.forebet.com/en/football-match-previews/25477-hoffenheim-seek-to-extend-unbeaten-run-as-union-berlin-look-to-disrupt-bundesliga-pace-at-prezero-arena",
    "country": "Germany",
    "league_name": "Bundesliga",
    "home_correct_score": 3,
    "away_correct_score": 1,
    "home_ht_score": 2,
    "away_ht_score": 0
  },
  {
    "home_team": "Holstein Kiel",
    "away_team": "Greuther Furth",
    "home_draw_odds": 1.19,
    "away_draw_odds": 2.01,
    "home_away_odds": 1.24,
    "date": "31 Jan",
    "time": "14:00",
    "game_url": "https://betway.co.za/event/soccer/germany/2-bundesliga/holstein-kiel-greuther-furth?eventId=61514990&fixtureType=highlights",
    "home_win": 1.66,
    "draw": 3.85,
    "away_win": 4.6,
    "home_draw_no_bet": 1.29,
    "away_draw_no_bet": 3.4,
    "total_over_1.5": 1.19,
    "total_under_3.5": 1.46,
    "BTTS_yes": 1.67,
    "BTTS_no": 2.12,
    "home_team_over_0.5": 1.13,
    "away_team_over_0.5": 1.45,
    "match_confidence": 96.43,
    "match_id": 2323230,
    "pred": "1",
    "home_pred_score": 2,
    "away_pred_score": 1,
    "prob_1": 46,
    "prob_x": 36,
    "prob_2": 18,
    "avg_goals": 2.79,
    "kelly": null,
    "game_link": "https://www.forebet.com/en/football/matches/holstein-kiel-greuther-fürth-2323230",
    "preview_link": null,
    "country": "Germany",
    "league_name": "2 Bundesliga",
    "home_correct_score": 1,
    "away_correct_score": 2,
    "home_ht_score": 0,
    "away_ht_score": 0
  },
  {
    "home_team": "VFL Bochum",
    "away_team": "Schalke 04",
    "home_draw_odds": 1.43,
    "away_draw_odds": 1.46,
    "home_away_odds": 1.31,
    "date": "31 Jan",
    "time": "14:00",
    "game_url": "https://betway.co.za/event/soccer/germany/2-bundesliga/vfl-bochum-schalke-04?eventId=61514992&fixtureType=highlights",
    "home_win": 2.49,
    "draw": 3.25,
    "away_win": 2.7,
    "home_draw_no_bet": 1.83,
    "away_draw_no_bet": 1.91,
    "total_over_1.5": 1.3,
    "total_under_3.5": 1.3,
    "BTTS_yes": 1.75,
    "BTTS_no": 2.0,
    "home_team_over_0.5": null,
    "away_team_over_0.5": 1.32,
    "match_confidence": 100.0,
    "match_id": 2323226,
    "pred": "2",
    "home_pred_score": 1,
    "away_pred_score": 2,
    "prob_1": 21,
    "prob_x": 25,
    "prob_2": 54,
    "avg_goals": 3.01,
    "kelly": 0.26,
    "game_link": "https://www.forebet.com/en/football/matches/bochum-schalke-04-2323226",
    "preview_link": null,
    "country": "Germany",
    "league_name": "2 Bundesliga",
    "home_correct_score": 2,
    "away_correct_score": 0,
    "home_ht_score": 2,
    "away_ht_score": 0
  },
  {
    "home_team": "Eintracht Braunschweig",
    "away_team": "Karlsruher SC",
    "home_draw_odds": 1.35,
    "away_draw_odds": 1.56,
    "home_away_odds": 1.3,
    "date": "31 Jan",
    "time": "14:00",
    "game_url": "https://betway.co.za/event/soccer/germany/2-bundesliga/eintracht-braunschweig-karlsruher-sc?eventId=61515004&fixtureType=highlights",
    "home_win": 2.23,
    "draw": 3.35,
    "away_win": 3.0,
    "home_draw_no_bet": 1.64,
    "away_draw_no_bet": 2.18,
    "total_over_1.5": 1.22,
    "total_under_3.5": 1.4,
    "BTTS_yes": 1.62,
    "BTTS_no": 2.21,
    "home_team_over_0.5": 1.22,
    "away_team_over_0.5": 1.31,
    "match_confidence": 100.0,
    "match_id": 2323228,
    "pred": "X",
    "home_pred_score": 1,
    "away_pred_score": 1,
    "prob_1": 29,
    "prob_x": 39,
    "prob_2": 32,
    "avg_goals": 2.0,
    "kelly": 0.15,
    "game_link": "https://www.forebet.com/en/football/matches/braunschweig-karlsruher-sc-2323228",
    "preview_link": null,
    "country": "Germany",
    "league_name": "2 Bundesliga",
    "home_correct_score": 1,
    "away_correct_score": 0,
    "home_ht_score": 1,
    "away_ht_score": 0
  },
  {
    "home_team": "1 FC Kaiserslautern",
    "away_team": "SV 07 Elversberg",
    "home_draw_odds": 1.48,
    "away_draw_odds": 1.44,
    "home_away_odds": 1.28,
    "date": "31 Jan",
    "time": "21:30",
    "game_url": "https://betway.co.za/event/soccer/germany/2-bundesliga/1-fc-kaiserslautern-sv-07-elversberg?eventId=61514998&fixtureType=highlights",
    "home_win": 2.6,
    "draw": 3.5,
    "away_win": 2.44,
    "home_draw_no_bet": 1.93,
    "away_draw_no_bet": 1.81,
    "total_over_1.5": 1.17,
    "total_under_3.5": 1.52,
    "BTTS_yes": 1.51,
    "BTTS_no": 2.46,
    "home_team_over_0.5": 1.23,
    "away_team_over_0.5": 1.21,
    "match_confidence": 95.83,
    "match_id": 2323227,
    "pred": "2",
    "home_pred_score": 2,
    "away_pred_score": 3,
    "prob_1": 30,
    "prob_x": 34,
    "prob_2": 36,
    "avg_goals": 3.4,
    "kelly": null,
    "game_link": "https://www.forebet.com/en/football/matches/kaiserslautern-sv-elversberg-2323227",
    "preview_link": null,
    "country": "Germany",
    "league_name": "2 Bundesliga",
    "home_correct_score": 1,
    "away_correct_score": 3,
    "home_ht_score": 1,
    "away_ht_score": 1
  },
  {
    "home_team": "1. FC Saarbrucken",
    "away_team": "VfL 1899 Osnabruck",
    "home_draw_odds": 1.42,
    "away_draw_odds": 1.49,
    "home_away_odds": 1.3,
    "date": "31 Jan",
    "time": "15:00",
    "game_url": "https://betway.co.za/event/soccer/germany/3-liga/1-fc-saarbrucken-vfl-1899-osnabruck?eventId=61709380&fixtureType=highlights",
    "home_win": 2.4,
    "draw": 3.3,
    "away_win": 2.65,
    "home_draw_no_bet": null,
    "away_draw_no_bet": null,
    "total_over_1.5": 1.24,
    "total_under_3.5": 1.34,
    "BTTS_yes": 1.62,
    "BTTS_no": 2.06,
    "home_team_over_0.5": 1.24,
    "away_team_over_0.5": null,
    "match_confidence": 88.93,
    "match_id": 2323574,
    "pred": "2",
    "home_pred_score": 1,
    "away_pred_score": 3,
    "prob_1": 23,
    "prob_x": 32,
    "prob_2": 45,
    "avg_goals": 3.49,
    "kelly": 0.13,
    "game_link": "https://www.forebet.com/en/football/matches/saarbrücken-vfl-osnabruck-2323574",
    "preview_link": null,
    "country": "Germany",
    "league_name": "3 Liga",
    "home_correct_score": 0,
    "away_correct_score": 1,
    "home_ht_score": 0,
    "away_ht_score": 1
  },
  {
    "home_team": "Energie Cottbus",
    "away_team": "TSG Hoffenheim II U23",
    "home_draw_odds": 1.32,
    "away_draw_odds": 2.55,
    "home_away_odds": 1.32,
    "date": "31 Jan",
    "time": "15:00",
    "game_url": "https://betway.co.za/event/soccer/germany/3-liga/energie-cottbus-tsg-hoffenheim-ii-u23?eventId=61709386&fixtureType=highlights",
    "home_win": 1.98,
    "draw": 3.65,
    "away_win": 3.1,
    "home_draw_no_bet": null,
    "away_draw_no_bet": null,
    "total_over_1.5": 1.12,
    "total_under_3.5": 1.63,
    "BTTS_yes": 1.41,
    "BTTS_no": 2.55,
    "home_team_over_0.5": 1.12,
    "away_team_over_0.5": null,
    "match_confidence": 100.0,
    "match_id": 2323572,
    "pred": "2",
    "home_pred_score": 2,
    "away_pred_score": 3,
    "prob_1": 36,
    "prob_x": 24,
    "prob_2": 41,
    "avg_goals": 4.38,
    "kelly": 0.15,
    "game_link": "https://www.forebet.com/en/football/matches/energie-cottbus-hoffenheim-ii-2323572",
    "preview_link": null,
    "country": "Germany",
    "league_name": "3 Liga",
    "home_correct_score": 3,
    "away_correct_score": 1,
    "home_ht_score": 2,
    "away_ht_score": 1
  },
  {
    "home_team": "Hansa Rostock",
    "away_team": "FC Ingolstadt 04",
    "home_draw_odds": 1.19,
    "away_draw_odds": 2.04,
    "home_away_odds": 1.22,
    "date": "31 Jan",
    "time": "15:00",
    "game_url": "https://betway.co.za/event/soccer/germany/3-liga/hansa-rostock-fc-ingolstadt-04?eventId=61709388&fixtureType=highlights",
    "home_win": 1.62,
    "draw": 3.9,
    "away_win": 4.4,
    "home_draw_no_bet": null,
    "away_draw_no_bet": null,
    "total_over_1.5": 1.15,
    "total_under_3.5": 1.54,
    "BTTS_yes": 1.55,
    "BTTS_no": 2.2,
    "home_team_over_0.5": 1.1,
    "away_team_over_0.5": 1.37,
    "match_confidence": 100.0,
    "match_id": 2323575,
    "pred": "X",
    "home_pred_score": 1,
    "away_pred_score": 1,
    "prob_1": 33,
    "prob_x": 39,
    "prob_2": 28,
    "avg_goals": 2.2,
    "kelly": 0.17,
    "game_link": "https://www.forebet.com/en/football/matches/hansa-rostock-ingolstadt-2323575",
    "preview_link": null,
    "country": "Germany",
    "league_name": "3 Liga",
    "home_correct_score": 0,
    "away_correct_score": 3,
    "home_ht_score": 0,
    "away_ht_score": 2
  },
  {
    "home_team": "TSV 1860 Munich",
    "away_team": "Alemannia Aachen",
    "home_draw_odds": 1.3,
    "away_draw_odds": 1.67,
    "home_away_odds": 1.28,
    "date": "31 Jan",
    "time": "15:00",
    "game_url": "https://betway.co.za/event/soccer/germany/3-liga/tsv-1860-munich-alemannia-aachen?eventId=61709394&fixtureType=highlights",
    "home_win": 2.01,
    "draw": 3.4,
    "away_win": 3.25,
    "home_draw_no_bet": null,
    "away_draw_no_bet": null,
    "total_over_1.5": 1.22,
    "total_under_3.5": 1.36,
    "BTTS_yes": 1.63,
    "BTTS_no": 2.06,
    "home_team_over_0.5": 1.18,
    "away_team_over_0.5": 1.34,
    "match_confidence": 100.0,
    "match_id": 2323571,
    "pred": "1",
    "home_pred_score": 2,
    "away_pred_score": 1,
    "prob_1": 41,
    "prob_x": 34,
    "prob_2": 25,
    "avg_goals": 2.65,
    "kelly": null,
    "game_link": "https://www.forebet.com/en/football/matches/tsv-1860-alemannia-aachen-2323571",
    "preview_link": null,
    "country": "Germany",
    "league_name": "3 Liga",
    "home_correct_score": 2,
    "away_correct_score": 2,
    "home_ht_score": 1,
    "away_ht_score": 1
  },
  {
    "home_team": "1. FC Schweinfurt 05",
    "away_team": "Jahn Regensburg",
    "home_draw_odds": 1.68,
    "away_draw_odds": 1.3,
    "home_away_odds": 1.27,
    "date": "31 Jan",
    "time": "17:30",
    "game_url": "https://betway.co.za/event/soccer/germany/3-liga/1-fc-schweinfurt-05-jahn-regensburg?eventId=61709398&fixtureType=highlights",
    "home_win": 3.2,
    "draw": 3.5,
    "away_win": 1.99,
    "home_draw_no_bet": null,
    "away_draw_no_bet": null,
    "total_over_1.5": 1.17,
    "total_under_3.5": 1.47,
    "BTTS_yes": 1.52,
    "BTTS_no": 2.25,
    "home_team_over_0.5": null,
    "away_team_over_0.5": 1.15,
    "match_confidence": 100.0,
    "match_id": 2323579,
    "pred": "2",
    "home_pred_score": 1,
    "away_pred_score": 3,
    "prob_1": 32,
    "prob_x": 24,
    "prob_2": 43,
    "avg_goals": 3.13,
    "kelly": null,
    "game_link": "https://www.forebet.com/en/football/matches/schweinfurt-jahn-regensburg-2323579",
    "preview_link": null,
    "country": "Germany",
    "league_name": "3 Liga",
    "home_correct_score": 0,
    "away_correct_score": 1,
    "home_ht_score": 0,
    "away_ht_score": 1
  },
  {
    "home_team": "AS Far Rabat",
    "away_team": "JS Kabylie",
    "home_draw_odds": 1.15,
    "away_draw_odds": 1.92,
    "home_away_odds": 1.24,
    "date": "31 Jan",
    "time": "21:00",
    "game_url": "https://betway.co.za/event/soccer/international-clubs/caf-champions-league/as-far-rabat-js-kabylie?eventId=65343448&fixtureType=highlights",
    "home_win": 1.64,
    "draw": 3.48,
    "away_win": 4.95,
    "home_draw_no_bet": 1.23,
    "away_draw_no_bet": 3.45,
    "total_over_1.5": 1.39,
    "total_under_3.5": 1.19,
    "BTTS_yes": 2.15,
    "BTTS_no": 1.58,
    "home_team_over_0.5": 1.2,
    "away_team_over_0.5": 1.74,
    "match_confidence": 100.0,
    "match_id": 2406925,
    "pred": "X",
    "home_pred_score": 1,
    "away_pred_score": 1,
    "prob_1": 34,
    "prob_x": 42,
    "prob_2": 24,
    "avg_goals": 1.81,
    "kelly": 0.17,
    "game_link": "https://www.forebet.com/en/football/matches/far-rabat-js-kabylie-2406925",
    "preview_link": null,
    "country": "International_Clubs",
    "league_name": "Caf Champions League",
    "home_correct_score": 1,
    "away_correct_score": 0,
    "home_ht_score": 0,
    "away_ht_score": 0
  },
  {
    "home_team": "SSC Napoli",
    "away_team": "ACF Fiorentina",
    "home_draw_odds": 1.18,
    "away_draw_odds": 1.96,
    "home_away_odds": 1.27,
    "date": "31 Jan",
    "time": "19:00",
    "game_url": "https://betway.co.za/event/soccer/italy/serie-a/ssc-napoli-acf-fiorentina?eventId=61061395&fixtureType=highlights",
    "home_win": 1.74,
    "draw": 3.5,
    "away_win": 4.8,
    "home_draw_no_bet": 1.28,
    "away_draw_no_bet": 3.5,
    "total_over_1.5": 1.31,
    "total_under_3.5": 1.3,
    "BTTS_yes": 1.92,
    "BTTS_no": 1.82,
    "home_team_over_0.5": 1.18,
    "away_team_over_0.5": 1.61,
    "match_confidence": 100.0,
    "match_id": 2344433,
    "pred": "1",
    "home_pred_score": null,
    "away_pred_score": null,
    "prob_1": null,
    "prob_x": null,
    "prob_2": null,
    "avg_goals": null,
    "kelly": null,
    "game_link": "https://www.forebet.com/en/football/matches/napoli-fiorentina-2344433",
    "preview_link": null,
    "country": "Italy",
    "league_name": "Serie A",
    "home_correct_score": 2,
    "away_correct_score": 1,
    "home_ht_score": 1,
    "away_ht_score": 0
  },
  {
    "home_team": "Cagliari Calcio",
    "away_team": "Hellas Verona",
    "home_draw_odds": 1.26,
    "away_draw_odds": 1.6,
    "home_away_odds": 1.36,
    "date": "31 Jan",
    "time": "21:45",
    "game_url": "https://betway.co.za/event/soccer/italy/serie-a/cagliari-calcio-hellas-verona?eventId=61061387&fixtureType=highlights",
    "home_win": 2.19,
    "draw": 2.95,
    "away_win": 3.65,
    "home_draw_no_bet": 1.5,
    "away_draw_no_bet": 2.49,
    "total_over_1.5": 1.47,
    "total_under_3.5": 1.18,
    "BTTS_yes": 2.09,
    "BTTS_no": 1.69,
    "home_team_over_0.5": 1.32,
    "away_team_over_0.5": 1.58,
    "match_confidence": 100.0,
    "match_id": 2344434,
    "pred": "1",
    "home_pred_score": null,
    "away_pred_score": null,
    "prob_1": null,
    "prob_x": null,
    "prob_2": null,
    "avg_goals": null,
    "kelly": null,
    "game_link": "https://www.forebet.com/en/football/matches/cagliari-verona-2344434",
    "preview_link": null,
    "country": "Italy",
    "league_name": "Serie A",
    "home_correct_score": 4,
    "away_correct_score": 0,
    "home_ht_score": 2,
    "away_ht_score": 0
  },
  {
    "home_team": "US Avellino",
    "away_team": "Cesena FC",
    "home_draw_odds": 1.54,
    "away_draw_odds": 1.33,
    "home_away_odds": 1.33,
    "date": "31 Jan",
    "time": "16:00",
    "game_url": "https://betway.co.za/event/soccer/italy/serie-b/us-avellino-cesena-fc?eventId=62484054&fixtureType=highlights",
    "home_win": 3.05,
    "draw": 3.1,
    "away_win": 2.28,
    "home_draw_no_bet": 2.16,
    "away_draw_no_bet": 1.62,
    "total_over_1.5": 1.36,
    "total_under_3.5": 1.22,
    "BTTS_yes": 1.88,
    "BTTS_no": 1.83,
    "home_team_over_0.5": 1.42,
    "away_team_over_0.5": 1.3,
    "match_confidence": 100.0,
    "match_id": 2355722,
    "pred": "2",
    "home_pred_score": 1,
    "away_pred_score": 2,
    "prob_1": 33,
    "prob_x": 30,
    "prob_2": 37,
    "avg_goals": 2.63,
    "kelly": null,
    "game_link": "https://www.forebet.com/en/football/matches/avellino-cesena-2355722",
    "preview_link": null,
    "country": "Italy",
    "league_name": "Serie B",
    "home_correct_score": 3,
    "away_correct_score": 1,
    "home_ht_score": 2,
    "away_ht_score": 1
  },
  {
    "home_team": "Empoli",
    "away_team": "Modena FC",
    "home_draw_odds": 1.62,
    "away_draw_odds": 1.29,
    "home_away_odds": 1.32,
    "date": "31 Jan",
    "time": "16:00",
    "game_url": "https://betway.co.za/event/soccer/italy/serie-b/empoli-modena-fc?eventId=62484058&fixtureType=highlights",
    "home_win": 3.4,
    "draw": 3.15,
    "away_win": 2.1,
    "home_draw_no_bet": 2.39,
    "away_draw_no_bet": 1.51,
    "total_over_1.5": 1.35,
    "total_under_3.5": 1.23,
    "BTTS_yes": 1.88,
    "BTTS_no": 1.82,
    "home_team_over_0.5": 1.47,
    "away_team_over_0.5": 1.27,
    "match_confidence": 100.0,
    "match_id": 2355716,
    "pred": "X",
    "home_pred_score": 1,
    "away_pred_score": 1,
    "prob_1": 35,
    "prob_x": 39,
    "prob_2": 26,
    "avg_goals": 2.07,
    "kelly": 0.1,
    "game_link": "https://www.forebet.com/en/football/matches/empoli-modena-fc-2355716",
    "preview_link": null,
    "country": "Italy",
    "league_name": "Serie B",
    "home_correct_score": 0,
    "away_correct_score": 0,
    "home_ht_score": 0,
    "away_ht_score": 0
  },
  {
    "home_team": "Virtus Entella",
    "away_team": "Frosinone Calcio",
    "home_draw_odds": 1.56,
    "away_draw_odds": 1.33,
    "home_away_odds": 1.32,
    "date": "31 Jan",
    "time": "16:00",
    "game_url": "https://betway.co.za/event/soccer/italy/serie-b/virtus-entella-frosinone-calcio?eventId=62484060&fixtureType=highlights",
    "home_win": 3.05,
    "draw": 3.15,
    "away_win": 2.26,
    "home_draw_no_bet": 2.19,
    "away_draw_no_bet": 1.61,
    "total_over_1.5": 1.28,
    "total_under_3.5": 1.29,
    "BTTS_yes": 1.74,
    "BTTS_no": 1.98,
    "home_team_over_0.5": 1.37,
    "away_team_over_0.5": 1.25,
    "match_confidence": 100.0,
    "match_id": 2355719,
    "pred": "2",
    "home_pred_score": 0,
    "away_pred_score": 3,
    "prob_1": 16,
    "prob_x": 30,
    "prob_2": 54,
    "avg_goals": 2.58,
    "kelly": 0.19,
    "game_link": "https://www.forebet.com/en/football/matches/virtus-entella-frosinone-2355719",
    "preview_link": null,
    "country": "Italy",
    "league_name": "Serie B",
    "home_correct_score": 1,
    "away_correct_score": 1,
    "home_ht_score": 0,
    "away_ht_score": 0
  },
  {
    "home_team": "FC Sudtirol Bolzano",
    "away_team": "US Catanzaro",
    "home_draw_odds": 1.31,
    "away_draw_odds": 1.54,
    "home_away_odds": 1.36,
    "date": "31 Jan",
    "time": "16:00",
    "game_url": "https://betway.co.za/event/soccer/italy/serie-b/fc-sudtirol-bolzano-us-catanzaro?eventId=62484070&fixtureType=highlights",
    "home_win": 2.28,
    "draw": 2.9,
    "away_win": 3.25,
    "home_draw_no_bet": 1.59,
    "away_draw_no_bet": 2.22,
    "total_over_1.5": 1.37,
    "total_under_3.5": 1.22,
    "BTTS_yes": 1.88,
    "BTTS_no": 1.82,
    "home_team_over_0.5": 1.3,
    "away_team_over_0.5": 1.44,
    "match_confidence": 95.45,
    "match_id": 2355715,
    "pred": "X",
    "home_pred_score": 1,
    "away_pred_score": 1,
    "prob_1": 25,
    "prob_x": 43,
    "prob_2": 32,
    "avg_goals": 2.3,
    "kelly": 0.15,
    "game_link": "https://www.forebet.com/en/football/matches/fc-südtirol-catanzaro-2355715",
    "preview_link": null,
    "country": "Italy",
    "league_name": "Serie B",
    "home_correct_score": 2,
    "away_correct_score": 1,
    "home_ht_score": 2,
    "away_ht_score": 1
  },
  {
    "home_team": "Venezia FC",
    "away_team": "Carrarese Calcio",
    "home_draw_odds": 1.1,
    "away_draw_odds": 2.55,
    "home_away_odds": 1.17,
    "date": "31 Jan",
    "time": "16:00",
    "game_url": "https://betway.co.za/event/soccer/italy/serie-b/venezia-fc-carrarese-calcio?eventId=62484072&fixtureType=highlights",
    "home_win": 1.38,
    "draw": 4.6,
    "away_win": 6.8,
    "home_draw_no_bet": 1.14,
    "away_draw_no_bet": 5.0,
    "total_over_1.5": 1.18,
    "total_under_3.5": 1.47,
    "BTTS_yes": 1.84,
    "BTTS_no": 1.86,
    "home_team_over_0.5": null,
    "away_team_over_0.5": 1.66,
    "match_confidence": 100.0,
    "match_id": 2355721,
    "pred": "1",
    "home_pred_score": 3,
    "away_pred_score": 1,
    "prob_1": 46,
    "prob_x": 25,
    "prob_2": 29,
    "avg_goals": 3.08,
    "kelly": null,
    "game_link": "https://www.forebet.com/en/football/matches/venezia-carrarese-calcio-2355721",
    "preview_link": null,
    "country": "Italy",
    "league_name": "Serie B",
    "home_correct_score": 2,
    "away_correct_score": 1,
    "home_ht_score": 1,
    "away_ht_score": 0
  },
  {
    "home_team": "Delfino Pescara",
    "away_team": "Mantova 1911",
    "home_draw_odds": 1.38,
    "away_draw_odds": 1.52,
    "home_away_odds": 1.3,
    "date": "31 Jan",
    "time": "18:15",
    "game_url": "https://betway.co.za/event/soccer/italy/serie-b/delfino-pescara-mantova-1911?eventId=62484064&fixtureType=highlights",
    "home_win": 2.32,
    "draw": 3.3,
    "away_win": 2.8,
    "home_draw_no_bet": 1.7,
    "away_draw_no_bet": 2.03,
    "total_over_1.5": 1.23,
    "total_under_3.5": 1.37,
    "BTTS_yes": 1.62,
    "BTTS_no": 2.16,
    "home_team_over_0.5": 1.23,
    "away_team_over_0.5": 1.29,
    "match_confidence": 94.44,
    "match_id": 2355720,
    "pred": "X",
    "home_pred_score": 1,
    "away_pred_score": 1,
    "prob_1": 32,
    "prob_x": 42,
    "prob_2": 26,
    "avg_goals": 2.0,
    "kelly": 0.18,
    "game_link": "https://www.forebet.com/en/football/matches/pescara-mantova-fc-2355720",
    "preview_link": null,
    "country": "Italy",
    "league_name": "Serie B",
    "home_correct_score": 2,
    "away_correct_score": 2,
    "home_ht_score": 1,
    "away_ht_score": 1
  },
  {
    "home_team": "Sampdoria Genoa",
    "away_team": "Spezia Calcio",
    "home_draw_odds": 1.28,
    "away_draw_odds": 1.63,
    "home_away_odds": 1.32,
    "date": "31 Jan",
    "time": "20:30",
    "game_url": "https://betway.co.za/event/soccer/italy/serie-b/sampdoria-genoa-spezia-calcio?eventId=62484068&fixtureType=highlights",
    "home_win": 2.07,
    "draw": 3.15,
    "away_win": 3.45,
    "home_draw_no_bet": 1.49,
    "away_draw_no_bet": 2.44,
    "total_over_1.5": 1.38,
    "total_under_3.5": 1.21,
    "BTTS_yes": 1.95,
    "BTTS_no": 1.76,
    "home_team_over_0.5": 1.28,
    "away_team_over_0.5": 1.51,
    "match_confidence": 100.0,
    "match_id": 2355714,
    "pred": "X",
    "home_pred_score": 0,
    "away_pred_score": 0,
    "prob_1": 34,
    "prob_x": 36,
    "prob_2": 30,
    "avg_goals": 2.13,
    "kelly": 0.06,
    "game_link": "https://www.forebet.com/en/football/matches/sampdoria-spezia-2355714",
    "preview_link": null,
    "country": "Italy",
    "league_name": "Serie B",
    "home_correct_score": 1,
    "away_correct_score": 0,
    "home_ht_score": 0,
    "away_ht_score": 0
  },
  {
    "home_team": "Paris FC",
    "away_team": "Olympique Marseille",
    "home_draw_odds": 1.79,
    "away_draw_odds": 1.26,
    "home_away_odds": 1.26,
    "date": "31 Jan",
    "time": "18:00",
    "game_url": "https://betway.co.za/event/soccer/france/ligue-1/paris-fc-olympique-marseille?eventId=61526328&fixtureType=highlights",
    "home_win": 3.6,
    "draw": 3.7,
    "away_win": 1.92,
    "home_draw_no_bet": 2.75,
    "away_draw_no_bet": 1.42,
    "total_over_1.5": 1.21,
    "total_under_3.5": 1.44,
    "BTTS_yes": 1.64,
    "BTTS_no": 2.18,
    "home_team_over_0.5": 1.38,
    "away_team_over_0.5": 1.16,
    "match_confidence": 100.0,
    "match_id": 2316293,
    "pred": "2",
    "home_pred_score": 1,
    "away_pred_score": 3,
    "prob_1": 21,
    "prob_x": 14,
    "prob_2": 66,
    "avg_goals": 5.17,
    "kelly": 0.25,
    "game_link": "https://www.forebet.com/en/football/matches/paris-fc-olympique-marseille-2316293",
    "preview_link": "https://www.forebet.com/en/football-match-previews/25321-olympique-marseille-aim-to-continue-strong-run-against-paris-fc-at-stade-jean-bouin",
    "country": "France",
    "league_name": "Ligue1",
    "home_correct_score": 2,
    "away_correct_score": 2,
    "home_ht_score": 0,
    "away_ht_score": 1
  },
  {
    "home_team": "FC Lorient",
    "away_team": "FC Nantes",
    "home_draw_odds": 1.21,
    "away_draw_odds": 1.84,
    "home_away_odds": 1.28,
    "date": "31 Jan",
    "time": "20:00",
    "game_url": "https://betway.co.za/event/soccer/france/ligue-1/fc-lorient-fc-nantes?eventId=61526336&fixtureType=highlights",
    "home_win": 1.83,
    "draw": 3.5,
    "away_win": 4.2,
    "home_draw_no_bet": 1.35,
    "away_draw_no_bet": 3.05,
    "total_over_1.5": 1.33,
    "total_under_3.5": 1.28,
    "BTTS_yes": 1.91,
    "BTTS_no": 1.83,
    "home_team_over_0.5": 1.21,
    "away_team_over_0.5": 1.56,
    "match_confidence": 100.0,
    "match_id": 2316294,
    "pred": "1",
    "home_pred_score": null,
    "away_pred_score": null,
    "prob_1": null,
    "prob_x": null,
    "prob_2": null,
    "avg_goals": null,
    "kelly": null,
    "game_link": "https://www.forebet.com/en/football/matches/lorient-nantes-2316294",
    "preview_link": null,
    "country": "France",
    "league_name": "Ligue1",
    "home_correct_score": 2,
    "away_correct_score": 1,
    "home_ht_score": 1,
    "away_ht_score": 0
  },
  {
    "home_team": "USL Dunkerque",
    "away_team": "FC Annecy",
    "home_draw_odds": 1.24,
    "away_draw_odds": 1.7,
    "home_away_odds": 1.32,
    "date": "31 Jan",
    "time": "15:00",
    "game_url": "https://betway.co.za/event/soccer/france/ligue-2/usl-dunkerque-fc-annecy?eventId=61527720&fixtureType=highlights",
    "home_win": 1.98,
    "draw": 3.1,
    "away_win": 3.8,
    "home_draw_no_bet": 1.42,
    "away_draw_no_bet": 2.65,
    "total_over_1.5": 1.36,
    "total_under_3.5": 1.22,
    "BTTS_yes": 1.93,
    "BTTS_no": 1.78,
    "home_team_over_0.5": 1.25,
    "away_team_over_0.5": 1.53,
    "match_confidence": 100.0,
    "match_id": 2333828,
    "pred": "2",
    "home_pred_score": 1,
    "away_pred_score": 2,
    "prob_1": 34,
    "prob_x": 28,
    "prob_2": 38,
    "avg_goals": 3.05,
    "kelly": 0.18,
    "game_link": "https://www.forebet.com/en/football/matches/dunkerque-annecy-2333828",
    "preview_link": null,
    "country": "France",
    "league_name": "Ligue2",
    "home_correct_score": 0,
    "away_correct_score": 1,
    "home_ht_score": 0,
    "away_ht_score": 1
  },
  {
    "home_team": "Troyes AC",
    "away_team": "Le Mans FC",
    "home_draw_odds": 1.27,
    "away_draw_odds": 1.67,
    "home_away_odds": 1.32,
    "date": "31 Jan",
    "time": "15:00",
    "game_url": "https://betway.co.za/event/soccer/france/ligue-2/troyes-ac-le-mans-fc?eventId=61527726&fixtureType=highlights",
    "home_win": 2.03,
    "draw": 3.15,
    "away_win": 3.55,
    "home_draw_no_bet": 1.46,
    "away_draw_no_bet": 2.5,
    "total_over_1.5": 1.35,
    "total_under_3.5": 1.23,
    "BTTS_yes": 1.89,
    "BTTS_no": 1.81,
    "home_team_over_0.5": 1.25,
    "away_team_over_0.5": 1.49,
    "match_confidence": 100.0,
    "match_id": 2333827,
    "pred": "X",
    "home_pred_score": 1,
    "away_pred_score": 1,
    "prob_1": 30,
    "prob_x": 37,
    "prob_2": 33,
    "avg_goals": 2.47,
    "kelly": 0.07,
    "game_link": "https://www.forebet.com/en/football/matches/troyes-le-mans-fc-2333827",
    "preview_link": null,
    "country": "France",
    "league_name": "Ligue2",
    "home_correct_score": 0,
    "away_correct_score": 2,
    "home_ht_score": 0,
    "away_ht_score": 2
  },
  {
    "home_team": "AS Saint-Etienne",
    "away_team": "US Boulogne",
    "home_draw_odds": 1.15,
    "away_draw_odds": 2.19,
    "home_away_odds": 1.21,
    "date": "31 Jan",
    "time": "21:00",
    "game_url": "https://betway.co.za/event/soccer/france/ligue-2/as-saintetienne-us-boulogne?eventId=62716727&fixtureType=highlights",
    "home_win": 1.54,
    "draw": 4.0,
    "away_win": 5.2,
    "home_draw_no_bet": 1.22,
    "away_draw_no_bet": 3.85,
    "total_over_1.5": 1.19,
    "total_under_3.5": 1.46,
    "BTTS_yes": 1.71,
    "BTTS_no": 2.01,
    "home_team_over_0.5": 1.11,
    "away_team_over_0.5": 1.51,
    "match_confidence": 100.0,
    "match_id": 2354746,
    "pred": "1",
    "home_pred_score": 2,
    "away_pred_score": 0,
    "prob_1": 50,
    "prob_x": 31,
    "prob_2": 19,
    "avg_goals": 2.13,
    "kelly": null,
    "game_link": "https://www.forebet.com/en/football/matches/saint-etienne-us-boulogne-2354746",
    "preview_link": null,
    "country": "France",
    "league_name": "Ligue2",
    "home_correct_score": 0,
    "away_correct_score": 1,
    "home_ht_score": 0,
    "away_ht_score": 1
  },
  {
    "home_team": "Valenciennes FC",
    "away_team": "US Orleans",
    "home_draw_odds": 1.42,
    "away_draw_odds": 1.47,
    "home_away_odds": 1.31,
    "date": "31 Jan",
    "time": "18:30",
    "game_url": "https://betway.co.za/event/soccer/france/national/valenciennes-fc-us-orleans?eventId=62117104&fixtureType=highlights",
    "home_win": 2.46,
    "draw": 3.2,
    "away_win": 2.65,
    "home_draw_no_bet": null,
    "away_draw_no_bet": null,
    "total_over_1.5": 1.27,
    "total_under_3.5": 1.29,
    "BTTS_yes": 1.69,
    "BTTS_no": 1.96,
    "home_team_over_0.5": 1.27,
    "away_team_over_0.5": 1.3,
    "match_confidence": 95.0,
    "match_id": 2334118,
    "pred": "1",
    "home_pred_score": 2,
    "away_pred_score": 0,
    "prob_1": 46,
    "prob_x": 19,
    "prob_2": 36,
    "avg_goals": 2.38,
    "kelly": 0.09,
    "game_link": "https://www.forebet.com/en/football/matches/valenciennes-fc-us-orléans-2334118",
    "preview_link": null,
    "country": "France",
    "league_name": "National",
    "home_correct_score": 0,
    "away_correct_score": 1,
    "home_ht_score": 0,
    "away_ht_score": 1
  },
  {
    "home_team": "AS Saint-Etienne",
    "away_team": "Le Havre AC",
    "home_draw_odds": 1.34,
    "away_draw_odds": 1.46,
    "home_away_odds": 1.3,
    "date": "31 Jan",
    "time": "16:00",
    "game_url": "https://betway.co.za/event/soccer/france/premiere-ligue-women/as-saintetienne-le-havre-ac?eventId=62033858&fixtureType=highlights",
    "home_win": 2.35,
    "draw": 3.09,
    "away_win": 2.86,
    "home_draw_no_bet": 1.66,
    "away_draw_no_bet": 2.01,
    "total_over_1.5": 1.29,
    "total_under_3.5": 1.27,
    "BTTS_yes": 1.72,
    "BTTS_no": 1.93,
    "home_team_over_0.5": 1.26,
    "away_team_over_0.5": 1.33,
    "match_confidence": 90.23,
    "match_id": 2370719,
    "pred": "2",
    "home_pred_score": 1,
    "away_pred_score": 2,
    "prob_1": 35,
    "prob_x": 27,
    "prob_2": 37,
    "avg_goals": 2.63,
    "kelly": 0.01,
    "game_link": "https://www.forebet.com/en/football/matches/saint-Étienne-w-le-havre-w-2370719",
    "preview_link": null,
    "country": "France",
    "league_name": "Division 1 Women",
    "home_correct_score": 1,
    "away_correct_score": 1,
    "home_ht_score": 0,
    "away_ht_score": 0
  },
  {
    "home_team": "RC Strasbourg",
    "away_team": "Dijon FCO",
    "home_draw_odds": 1.36,
    "away_draw_odds": 1.47,
    "home_away_odds": 1.28,
    "date": "31 Jan",
    "time": "18:00",
    "game_url": "https://betway.co.za/event/soccer/france/premiere-ligue-women/rc-strasbourg-dijon-fco?eventId=62033854&fixtureType=highlights",
    "home_win": 2.32,
    "draw": 3.28,
    "away_win": 2.75,
    "home_draw_no_bet": 1.68,
    "away_draw_no_bet": 1.98,
    "total_over_1.5": 1.3,
    "total_under_3.5": 1.26,
    "BTTS_yes": 1.76,
    "BTTS_no": 1.88,
    "home_team_over_0.5": 1.28,
    "away_team_over_0.5": 1.34,
    "match_confidence": 91.61,
    "match_id": 2370718,
    "pred": "X",
    "home_pred_score": 0,
    "away_pred_score": 0,
    "prob_1": 30,
    "prob_x": 42,
    "prob_2": 28,
    "avg_goals": 1.92,
    "kelly": 0.18,
    "game_link": "https://www.forebet.com/en/football/matches/strasbourg-w-dijon-w-2370718",
    "preview_link": null,
    "country": "France",
    "league_name": "Division 1 Women",
    "home_correct_score": 0,
    "away_correct_score": 3,
    "home_ht_score": 0,
    "away_ht_score": 1
  },
  {
    "home_team": "Marumo Gallants FC",
    "away_team": "AmaZulu FC",
    "home_draw_odds": 1.41,
    "away_draw_odds": 1.41,
    "home_away_odds": 1.37,
    "date": "31 Jan",
    "time": "15:30",
    "game_url": "https://betway.co.za/event/soccer/south-africa/premiership/marumo-gallants-fc-amazulu-fc?eventId=62670215&fixtureType=highlights",
    "home_win": 2.75,
    "draw": 2.9,
    "away_win": 2.75,
    "home_draw_no_bet": 1.87,
    "away_draw_no_bet": 1.87,
    "total_over_1.5": 1.55,
    "total_under_3.5": 1.14,
    "BTTS_yes": 2.21,
    "BTTS_no": 1.62,
    "home_team_over_0.5": 1.48,
    "away_team_over_0.5": null,
    "match_confidence": 100.0,
    "match_id": 2339275,
    "pred": "2",
    "home_pred_score": 0,
    "away_pred_score": 1,
    "prob_1": 28,
    "prob_x": 32,
    "prob_2": 40,
    "avg_goals": 1.48,
    "kelly": 0.11,
    "game_link": "https://www.forebet.com/en/football/matches/marumo-gallants-amazulu-fc-2339275",
    "preview_link": null,
    "country": "South_Africa",
    "league_name": "Premier League",
    "home_correct_score": 0,
    "away_correct_score": 1,
    "home_ht_score": 0,
    "away_ht_score": 0
  },
  {
    "home_team": "Chippa United FC",
    "away_team": "Durban City",
    "home_draw_odds": 1.53,
    "away_draw_odds": 1.28,
    "home_away_odds": 1.39,
    "date": "31 Jan",
    "time": "15:30",
    "game_url": "https://betway.co.za/event/soccer/south-africa/premiership/chippa-united-fc-durban-city?eventId=62670221&fixtureType=highlights",
    "home_win": 3.5,
    "draw": 2.8,
    "away_win": 2.33,
    "home_draw_no_bet": 2.32,
    "away_draw_no_bet": 1.57,
    "total_over_1.5": 1.71,
    "total_under_3.5": 1.09,
    "BTTS_yes": 2.55,
    "BTTS_no": 1.48,
    "home_team_over_0.5": 1.72,
    "away_team_over_0.5": 1.46,
    "match_confidence": 100.0,
    "match_id": 2339278,
    "pred": "2",
    "home_pred_score": 0,
    "away_pred_score": 2,
    "prob_1": 15,
    "prob_x": 26,
    "prob_2": 59,
    "avg_goals": 1.0,
    "kelly": 0.26,
    "game_link": "https://www.forebet.com/en/football/matches/chippa-united-durban-city-2339278",
    "preview_link": null,
    "country": "South_Africa",
    "league_name": "Premier League",
    "home_correct_score": 2,
    "away_correct_score": 0,
    "home_ht_score": 1,
    "away_ht_score": 0
  },
  {
    "home_team": "Orlando Pirates FC",
    "away_team": "Magesi FC",
    "home_draw_odds": 1.08,
    "away_draw_odds": 2.65,
    "home_away_odds": 1.19,
    "date": "31 Jan",
    "time": "18:00",
    "game_url": "https://betway.co.za/event/soccer/south-africa/premiership/orlando-pirates-fc-magesi-fc?eventId=68342386&fixtureType=highlights",
    "home_win": 1.38,
    "draw": 4.3,
    "away_win": 9.0,
    "home_draw_no_bet": 1.1,
    "away_draw_no_bet": 6.2,
    "total_over_1.5": 1.42,
    "total_under_3.5": 1.21,
    "BTTS_yes": 2.75,
    "BTTS_no": 1.42,
    "home_team_over_0.5": 1.15,
    "away_team_over_0.5": 2.33,
    "match_confidence": 100.0,
    "match_id": 2362325,
    "pred": "1",
    "home_pred_score": 1,
    "away_pred_score": 0,
    "prob_1": 61,
    "prob_x": 34,
    "prob_2": 5,
    "avg_goals": 1.42,
    "kelly": null,
    "game_link": "https://www.forebet.com/en/football/matches/orlando-pirates-magesi-fc-2362325",
    "preview_link": null,
    "country": "South_Africa",
    "league_name": "Premier League",
    "home_correct_score": 2,
    "away_correct_score": 0,
    "home_ht_score": 2,
    "away_ht_score": 0
  },
  {
    "home_team": "Polokwane City",
    "away_team": "Orbit College FC",
    "home_draw_odds": 1.19,
    "away_draw_odds": 1.74,
    "home_away_odds": 1.36,
    "date": "31 Jan",
    "time": "18:00",
    "game_url": "https://betway.co.za/event/soccer/south-africa/premiership/polokwane-city-orbit-college-fc?eventId=62670219&fixtureType=highlights",
    "home_win": 1.95,
    "draw": 2.95,
    "away_win": 4.6,
    "home_draw_no_bet": 1.34,
    "away_draw_no_bet": 3.1,
    "total_over_1.5": 1.65,
    "total_under_3.5": 1.11,
    "BTTS_yes": 2.55,
    "BTTS_no": 1.47,
    "home_team_over_0.5": 1.35,
    "away_team_over_0.5": 1.9,
    "match_confidence": 100.0,
    "match_id": 2339277,
    "pred": "1",
    "home_pred_score": 1,
    "away_pred_score": 0,
    "prob_1": 52,
    "prob_x": 21,
    "prob_2": 27,
    "avg_goals": 0.83,
    "kelly": null,
    "game_link": "https://www.forebet.com/en/football/matches/polokwane-city-orbit-college-fc-2339277",
    "preview_link": null,
    "country": "South_Africa",
    "league_name": "Premier League",
    "home_correct_score": 2,
    "away_correct_score": 2,
    "home_ht_score": 2,
    "away_ht_score": 0
  },
  {
    "home_team": "Rio Ave FC",
    "away_team": "FC Arouca",
    "home_draw_odds": 1.39,
    "away_draw_odds": 1.47,
    "home_away_odds": 1.33,
    "date": "31 Jan",
    "time": "20:00",
    "game_url": "https://betway.co.za/event/soccer/portugal/liga-portugal/rio-ave-fc-fc-arouca?eventId=61731220&fixtureType=highlights",
    "home_win": 2.48,
    "draw": 3.15,
    "away_win": 2.8,
    "home_draw_no_bet": 1.77,
    "away_draw_no_bet": 1.98,
    "total_over_1.5": 1.3,
    "total_under_3.5": 1.3,
    "BTTS_yes": 1.74,
    "BTTS_no": 2.01,
    "home_team_over_0.5": 1.29,
    "away_team_over_0.5": 1.34,
    "match_confidence": 100.0,
    "match_id": 2411098,
    "pred": "X",
    "home_pred_score": null,
    "away_pred_score": null,
    "prob_1": null,
    "prob_x": null,
    "prob_2": null,
    "avg_goals": null,
    "kelly": null,
    "game_link": "https://www.forebet.com/en/football/matches/rio-ave-fc-arouca-2411098",
    "preview_link": null,
    "country": "Portugal",
    "league_name": "Liga Portugal",
    "home_correct_score": 0,
    "away_correct_score": 3,
    "home_ht_score": 0,
    "away_ht_score": 1
  },
  {
    "home_team": "FC Alverca SAD",
    "away_team": "Estrela Amadora",
    "home_draw_odds": 1.28,
    "away_draw_odds": 1.65,
    "home_away_odds": 1.32,
    "date": "31 Jan",
    "time": "22:30",
    "game_url": "https://betway.co.za/event/soccer/portugal/liga-portugal/fc-alverca-sad-estrela-amadora?eventId=61731230&fixtureType=highlights",
    "home_win": 2.07,
    "draw": 3.2,
    "away_win": 3.5,
    "home_draw_no_bet": 1.5,
    "away_draw_no_bet": 2.49,
    "total_over_1.5": 1.36,
    "total_under_3.5": 1.23,
    "BTTS_yes": 1.92,
    "BTTS_no": 1.82,
    "home_team_over_0.5": 1.27,
    "away_team_over_0.5": 1.49,
    "match_confidence": 100.0,
    "match_id": 2411100,
    "pred": "1",
    "home_pred_score": null,
    "away_pred_score": null,
    "prob_1": null,
    "prob_x": null,
    "prob_2": null,
    "avg_goals": null,
    "kelly": null,
    "game_link": "https://www.forebet.com/en/football/matches/fc-alverca-estrela-amadora-2411100",
    "preview_link": null,
    "country": "Portugal",
    "league_name": "Liga Portugal",
    "home_correct_score": 1,
    "away_correct_score": 1,
    "home_ht_score": 0,
    "away_ht_score": 0
  },
  {
    "home_team": "FC Felgueiras 1932",
    "away_team": "GD Chaves",
    "home_draw_odds": 1.3,
    "away_draw_odds": 1.51,
    "home_away_odds": 1.3,
    "date": "31 Jan",
    "time": "13:00",
    "game_url": "https://betway.co.za/event/soccer/portugal/liga-portugal-2/fc-felgueiras-1932-gd-chaves?eventId=61732036&fixtureType=highlights",
    "home_win": 2.21,
    "draw": 3.13,
    "away_win": 3.06,
    "home_draw_no_bet": 1.58,
    "away_draw_no_bet": 2.15,
    "total_over_1.5": 1.33,
    "total_under_3.5": 1.23,
    "BTTS_yes": 1.82,
    "BTTS_no": 1.82,
    "home_team_over_0.5": 1.27,
    "away_team_over_0.5": 1.4,
    "match_confidence": 100.0,
    "match_id": 2345195,
    "pred": "1",
    "home_pred_score": 1,
    "away_pred_score": 0,
    "prob_1": 35,
    "prob_x": 33,
    "prob_2": 32,
    "avg_goals": 1.79,
    "kelly": null,
    "game_link": "https://www.forebet.com/en/football/matches/fc-felgueiras-gd-chaves-2345195",
    "preview_link": null,
    "country": "Portugal",
    "league_name": "Liga Portugal 2",
    "home_correct_score": 1,
    "away_correct_score": 0,
    "home_ht_score": 1,
    "away_ht_score": 0
  },
  {
    "home_team": "SC Farense",
    "away_team": "FC Porto B YOUTH",
    "home_draw_odds": 1.18,
    "away_draw_odds": 1.78,
    "home_away_odds": 1.18,
    "date": "31 Jan",
    "time": "20:00",
    "game_url": "https://betway.co.za/event/soccer/portugal/liga-portugal-2/sc-farense-fc-porto-b-youth?eventId=61732046&fixtureType=highlights",
    "home_win": 1.76,
    "draw": 3.37,
    "away_win": 4.27,
    "home_draw_no_bet": 1.3,
    "away_draw_no_bet": 3.0,
    "total_over_1.5": 1.3,
    "total_under_3.5": 1.26,
    "BTTS_yes": 1.86,
    "BTTS_no": 1.78,
    "home_team_over_0.5": 1.18,
    "away_team_over_0.5": null,
    "match_confidence": 100.0,
    "match_id": 2345200,
    "pred": "2",
    "home_pred_score": 0,
    "away_pred_score": 1,
    "prob_1": 32,
    "prob_x": 33,
    "prob_2": 35,
    "avg_goals": 1.98,
    "kelly": 0.16,
    "game_link": "https://www.forebet.com/en/football/matches/sc-farense-fc-porto-b-2345200",
    "preview_link": null,
    "country": "Portugal",
    "league_name": "Liga Portugal 2",
    "home_correct_score": 2,
    "away_correct_score": 3,
    "home_ht_score": 1,
    "away_ht_score": 2
  },
  {
    "home_team": "FC Vizela",
    "away_team": "Portimonense SAD",
    "home_draw_odds": 1.16,
    "away_draw_odds": 1.9,
    "home_away_odds": 1.23,
    "date": "31 Jan",
    "time": "22:30",
    "game_url": "https://betway.co.za/event/soccer/portugal/liga-portugal-2/fc-vizela-portimonense-sad?eventId=61732040&fixtureType=highlights",
    "home_win": 1.65,
    "draw": 3.56,
    "away_win": 4.71,
    "home_draw_no_bet": 1.25,
    "away_draw_no_bet": 3.35,
    "total_over_1.5": 1.27,
    "total_under_3.5": 1.29,
    "BTTS_yes": 1.85,
    "BTTS_no": 1.79,
    "home_team_over_0.5": 1.15,
    "away_team_over_0.5": 1.56,
    "match_confidence": 98.28,
    "match_id": 2345202,
    "pred": "1",
    "home_pred_score": 1,
    "away_pred_score": 0,
    "prob_1": 40,
    "prob_x": 31,
    "prob_2": 29,
    "avg_goals": 1.95,
    "kelly": null,
    "game_link": "https://www.forebet.com/en/football/matches/fc-vizela-portimonense-sc-2345202",
    "preview_link": null,
    "country": "Portugal",
    "league_name": "Liga Portugal 2",
    "home_correct_score": 1,
    "away_correct_score": 1,
    "home_ht_score": 1,
    "away_ht_score": 0
  },
  {
    "home_team": "AZ Alkmaar",
    "away_team": "NEC Nijmegen",
    "home_draw_odds": 1.25,
    "away_draw_odds": 1.84,
    "home_away_odds": 1.23,
    "date": "31 Jan",
    "time": "17:30",
    "game_url": "https://betway.co.za/event/soccer/netherlands/eredivisie/az-alkmaar-nec-nijmegen?eventId=61320041&fixtureType=highlights",
    "home_win": 1.81,
    "draw": 3.95,
    "away_win": 3.65,
    "home_draw_no_bet": 1.4,
    "away_draw_no_bet": 2.8,
    "total_over_1.5": 1.13,
    "total_under_3.5": 1.68,
    "BTTS_yes": 1.46,
    "BTTS_no": 2.6,
    "home_team_over_0.5": 1.11,
    "away_team_over_0.5": 1.29,
    "match_confidence": 100.0,
    "match_id": 2316991,
    "pred": "X",
    "home_pred_score": 1,
    "away_pred_score": 1,
    "prob_1": 26,
    "prob_x": 45,
    "prob_2": 29,
    "avg_goals": 2.4,
    "kelly": 0.27,
    "game_link": "https://www.forebet.com/en/football/matches/az-alkmaar-nijmegen-2316991",
    "preview_link": "https://www.forebet.com/en/football-match-previews/25366-momentum-meets-consistency-az-alkmaar-and-nijmegen-set-for-eredivisie-standoff",
    "country": "Netherlands",
    "league_name": "Eredivisie",
    "home_correct_score": 1,
    "away_correct_score": 3,
    "home_ht_score": 1,
    "away_ht_score": 2
  },
  {
    "home_team": "PEC Zwolle",
    "away_team": "SC Telstar",
    "home_draw_odds": 1.39,
    "away_draw_odds": 1.55,
    "home_away_odds": 1.27,
    "date": "31 Jan",
    "time": "19:45",
    "game_url": "https://betway.co.za/event/soccer/netherlands/eredivisie/pec-zwolle-sc-telstar?eventId=61320045&fixtureType=highlights",
    "home_win": 2.28,
    "draw": 3.55,
    "away_win": 2.75,
    "home_draw_no_bet": 1.71,
    "away_draw_no_bet": 2.07,
    "total_over_1.5": 1.18,
    "total_under_3.5": 1.49,
    "BTTS_yes": 1.54,
    "BTTS_no": 2.38,
    "home_team_over_0.5": 1.2,
    "away_team_over_0.5": 1.26,
    "match_confidence": 100.0,
    "match_id": 2316989,
    "pred": "1",
    "home_pred_score": null,
    "away_pred_score": null,
    "prob_1": null,
    "prob_x": null,
    "prob_2": null,
    "avg_goals": null,
    "kelly": null,
    "game_link": "https://www.forebet.com/en/football/matches/pec-zwolle-sc-telstar-2316989",
    "preview_link": null,
    "country": "Netherlands",
    "league_name": "Eredivisie",
    "home_correct_score": 4,
    "away_correct_score": 1,
    "home_ht_score": 1,
    "away_ht_score": 0
  },
  {
    "home_team": "Sparta Rotterdam",
    "away_team": "FC Groningen",
    "home_draw_odds": 1.45,
    "away_draw_odds": 1.45,
    "home_away_odds": 1.3,
    "date": "31 Jan",
    "time": "22:00",
    "game_url": "https://betway.co.za/event/soccer/netherlands/eredivisie/sparta-rotterdam-fc-groningen?eventId=61320039&fixtureType=highlights",
    "home_win": 2.55,
    "draw": 3.4,
    "away_win": 2.55,
    "home_draw_no_bet": 1.86,
    "away_draw_no_bet": 1.88,
    "total_over_1.5": 1.22,
    "total_under_3.5": 1.41,
    "BTTS_yes": 1.59,
    "BTTS_no": 2.26,
    "home_team_over_0.5": null,
    "away_team_over_0.5": 1.25,
    "match_confidence": 100.0,
    "match_id": 2316995,
    "pred": "X",
    "home_pred_score": null,
    "away_pred_score": null,
    "prob_1": null,
    "prob_x": null,
    "prob_2": null,
    "avg_goals": null,
    "kelly": null,
    "game_link": "https://www.forebet.com/en/football/matches/sparta-rotterdam-groningen-2316995",
    "preview_link": null,
    "country": "Netherlands",
    "league_name": "Eredivisie",
    "home_correct_score": 2,
    "away_correct_score": 0,
    "home_ht_score": 0,
    "away_ht_score": 0
  },
  {
    "home_team": "Helmond Sport",
    "away_team": "De Graafschap",
    "home_draw_odds": 1.54,
    "away_draw_odds": 1.43,
    "home_away_odds": 1.25,
    "date": "31 Jan",
    "time": "17:30",
    "game_url": "https://betway.co.za/event/soccer/netherlands/eerste-divisie/helmond-sport-de-graafschap?eventId=61380143&fixtureType=highlights",
    "home_win": 2.6,
    "draw": 3.7,
    "away_win": 2.25,
    "home_draw_no_bet": null,
    "away_draw_no_bet": null,
    "total_over_1.5": 1.1,
    "total_under_3.5": 1.74,
    "BTTS_yes": 1.35,
    "BTTS_no": 2.75,
    "home_team_over_0.5": 1.16,
    "away_team_over_0.5": 1.13,
    "match_confidence": 100.0,
    "match_id": 2334625,
    "pred": "2",
    "home_pred_score": 1,
    "away_pred_score": 2,
    "prob_1": 31,
    "prob_x": 22,
    "prob_2": 47,
    "avg_goals": 3.11,
    "kelly": 0.06,
    "game_link": "https://www.forebet.com/en/football/matches/helmond-sport-de-graafschap-2334625",
    "preview_link": null,
    "country": "Netherlands",
    "league_name": "Erstedivision",
    "home_correct_score": 0,
    "away_correct_score": 0,
    "home_ht_score": 0,
    "away_ht_score": 0
  }
]